Workbook
Name _z3dy4z: '_参数'!$B$2:$D$2
Name _z7qs7z: '_参数'!$B$3:$D$3
Name _zs8gul: '_参数'!$B$4:$J$4
Name _z7rtb0: '_参数'!$B$5:$J$5
Name _zx3hze: '_参数'!$B$6:$J$6
Name _zg5rek: '_参数'!$B$7:$J$7
Name _zvd8oo: '_参数'!$B$8:$J$8
Name _z8uul7: '_参数'!$B$9:$J$9
Name _zmd2n1: '_参数'!$B$10:$J$10
Name _zrss8w: '_参数'!$B$11:$J$11
Name _zxylnr: '_参数'!$B$12:$J$12
Name _zcmix6: '_参数'!$B$13:$J$13
Name _zc9vmb: '_参数'!$B$14:$J$14
Name _zmt7yq: '_参数'!$B$15:$J$15
Name _zgrhmu: '_参数'!$B$16:$J$16
Name _z2124k: '_参数'!$B$17:$J$17
Name _zqq9kl: '_参数'!$B$18:$J$18
Name _z24fjs: '_参数'!$B$19:$J$19
Name _zziz19: '_参数'!$B$20:$J$20
Name _zg9g0j: '_参数'!$B$21:$J$21
Name _zpq4om: '_参数'!$B$22:$J$22
Name _zs2zbw: '_参数'!$B$23:$J$23
Name _zjyrt0: '_参数'!$B$24:$J$24
Name _zy9h20: '_参数'!$B$25:$J$25
Name _zvhtq5: '_参数'!$B$26:$J$26
Name _z8a1yw: '_参数'!$B$27:$J$27
Name _zw9i4c: '_参数'!$B$28:$J$28
Name _z83gdf: '_参数'!$B$29:$J$29
Name _zrngfq: '_参数'!$B$30:$J$30
Name _z34nes: '_参数'!$B$31:$J$31
Name _zsyvua: '_参数'!$B$32:$J$32
Name _ztu197: '_参数'!$B$33:$J$33
Name _zdz3nh: '_参数'!$B$34:$J$34
Name _z59qak: '_参数'!$B$35:$J$35
Name _z7g7nz: '_参数'!$B$36:$J$36
Name _zuo7z3: '_参数'!$B$37:$J$37
Name _zkdmvf: '_参数'!$B$38:$D$38
Name _zt1gjv: '_参数'!$B$39:$D$39
Name _zobook: '测算'!$C$5
Name _zhoj8r: '测算'!$C$7
Name _zqeqjw: '测算'!$C$11
Name _zzg0id: '测算'!$C$12
Name _zv2cfz: '测算'!$C$13
Name _zqixf0: '测算'!$C$14
Name _zh76h3: '测算'!$C$15
Name _zcyms1: '测算'!$C$16
Name _zghrhb: '测算'!$C$17
Name _zecdlb: '测算'!$C$20
Name _z75lzf: '测算'!$C$21
Name _zh30bl: '测算'!$C$22
Name _zfbc18: '测算'!$C$23
Name _zlghw4: '测算'!$C$24
Name _zofnoh: '测算'!$C$25
Name _zzd9na: '测算'!$C$28
Name _zks9j8: '测算'!$C$29
Name _zx0gw6: '测算'!$C$30
Name _z9rhi7: '测算'!$C$31
Name _zva2xn: '测算'!$C$32
Name _z1sub1: '测算'!$C$33
Name _zk03a3: '测算'!$C$34

Sheet 说明
B2: 智能微电网经济评价 v3.3 · 介子九维 JIEZIJIUWEI
B3: 版本 v3.1 · 2026年7月13日 · 说明页补充就近消纳输配电费的1192号文单一容量制公式：就近消纳输配电费 = 容量电价 × 接入容量 × 12 ＋ 输配电度价 × 平均负荷率 × 730 × 12 × 接入容量，便于理解该项费用的构成。本工作簿该路径电价参数已按所选场景预置，此为纯文案说明，不改变计算结果。
B4: 来源：第四监管周期省级输配电价表（附件1），更新日期2026-07-10。区域电网输电价格表（附件2）仅在网站独立查询，不自动计入本测算公式。
B5: 分层测算说明
B6: 电量结构与费用结构（首年电量平衡、购电费、需量电费与收益七分项）按12个月×工作日/休息日共24个典型日的逐小时调度模拟预先算定，收入「测算」表。3个电价场景与3种典型日负荷形态两个选项各自独立、任意组合均已预设结果，用两个下拉选择；场景内的投资、融资、折旧、税务、折现等财务参数均可自由调整，全簿公式即时重算。需要其他电价路径、负荷曲线或资产组合时，请使用介子九维小程序在线测算。
B8: 电价场景
B9: 场景1 参考算例（代理购电·按需量）：山东并网型园区微电网，电网代理购电分时电价，需量计费；引擎参考算例原参数。
B10: 场景2 市场化购电（按需量）：同一资产与负荷，改为市场化交易购电（各档市场购电价+输配等平加），需量计费。
B11: 场景3 代理购电（按容量计费）：同一资产与负荷，代理购电路径，现行容（需）量电费改按变压器容量计费。
B13: 典型日负荷形态
B14: 白天生产型：负荷集中于白班，与光伏出力叠合度高，日间需量峰值明显。
B15: 晚高峰型：负荷晚间抬升，储能放电价值前移，晚间需量峰值最高。
... B39: 需求响应补偿标准、充电服务费、余电上网机制电量比例与结算价等场景内嵌参数为演示取值，正式测算前请通过介子九维小程序按项目所在地核实后重新出数。

Sheet 总览
B1: 智能微电网经济评价 · 总览 | P1: 介子九维 JIEZIJIUWEI
B2: ="所选场景下：税后全投资内部收益率 "&TEXT(_z3ewnh,"0.00%")&"，综合到户电价 "&TEXT(_zmbbnb,"0.000")&" 元/kWh，年节省 "&TEXT(_zbx4ou,"#,##0")&" 万元"
B4: 综合到户电价 | F4: 全投资内部收益率（税后） | J4: 资本金内部收益率 | N4: 静态回收期 | R4: 年节省额
B5: =_zmbbnb | F5: =_z3ewnh | J5: =_z2tbwe | N5: =_z3lcbu | R5: =_zbx4ou
B6: 元/kWh | F6: 主评价指标 | N6: 年 | R6: 万元
B41: 结果随「测算」表输入即时更新；测算口径与边界声明见「说明」。 | P41: 介子九维 JIEZIJIUWEI

Sheet _参数
A1: 典型场景数据
A2: 电价场景 | B2: 参考算例（代理购电·按需量） | C2: 市场化购电（按需量） | D2: 代理购电（按容量计费）
A3: 负荷形态 | B3: 白天生产型 | C3: 晚高峰型 | D3: 连续三班型
A4: 年可用发电量（万kWh） | B4: 1100 | C4: 1100 | D4: 1100 | E4: 1100 | F4: 1100 | G4: 1100 | H4: 1100 | I4: 1100 | J4: 1100
A5: 年自发自用电量（万kWh） | B5: 1100 | C5: 1100 | D5: 1100 | E5: 1100 | F5: 1100 | G5: 1100 | H5: 1100 | I5: 1100 | J5: 1100
A6: 年余电上网电量（万kWh） | B6: 0 | C6: 0 | D6: 0 | E6: 0 | F6: 0 | G6: 0 | H6: 0 | I6: 0 | J6: 0
A7: 年下网购电量（万kWh） | B7: 5142.0395 | C7: 5148.5678 | D7: 5142.796 | E7: 5142.0395 | F7: 5148.5678 | G7: 5142.796 | H7: 5149.14 | I7: 5148.5678 | J7: 5148.775
A8: 柴发年发电量（万kWh） | B8: 0 | C8: 0 | D8: 0 | E8: 0 | F8: 0 | G8: 0 | H8: 0 | I8: 0 | J8: 0
A9: 储能年放电量（万kWh） | B9: 308.28957 | C9: 356.16369 | D9: 313.83725 | E9: 308.28957 | F9: 356.16369 | G9: 313.83725 | H9: 360.36 | I9: 356.16369 | J9: 357.68345
A10: 储能年谷时充电量（万kWh） | B10: 350.32906 | C10: 404.73146 | D10: 356.63323 | E10: 350.32906 | F10: 404.73146 | G10: 356.63323 | H10: 409.5 | I10: 404.73146 | J10: 406.45846
A11: 年总用电量（万kWh） | B11: 6200 | C11: 6200 | D11: 6200 | E11: 6200 | F11: 6200 | G11: 6200 | H11: 6200 | I11: 6200 | J11: 6200
A12: 年购电电度费（万元） | B12: 3303.4162 | C12: 3616.2544 | D12: 3280.1999 | E12: 3060.8975 | F12: 3266.9412 | G12: 3046.945 | H12: 3264.5918 | I12: 3618.2882 | J12: 3250.6221
A13: 年需量（容量）电费（万元） | B13: 386.95339 | C13: 641.435 | D13: 342.144 | E13: 386.95339 | F13: 641.435 | G13: 342.144 | H13: 316.8 | I13: 316.8 | J13: 316.8
A14: 年就近消纳输配电费（万元） | B14: 0 | C14: 0 | D14: 0 | E14: 0 | F14: 0 | G14: 0 | H14: 0 | I14: 0 | J14: 0
A15: 年政府性基金及附加（万元） | B15: 0 | C15: 0 | D15: 0 | E15: 0 | F15: 0 | G15: 0 | H15: 0 | I15: 0 | J15: 0
... A37: 柴发装机（MW） | B37: 2 | C37: 2 | D37: 2 | E37: 2 | F37: 2 | G37: 2 | H37: 2 | I37: 2 | J37: 2
A38: 电价场景说明 | B38: 山东并网型园区微电网，电网代理购电分时电价，需量计费；引擎参考算例原参数。 | C38: 同一资产与负荷，改为市场化交易购电（各档市场购电价+输配等平加），需量计费。 | D38: 同一资产与负荷，代理购电路径，现行容（需）量电费改按变压器容量计费。
A39: 典型日负荷形态说明 | B39: 负荷集中于白班，与光伏出力叠合度高，日间需量峰值明显。 | C39: 负荷晚间抬升，储能放电价值前移，晚间需量峰值最高。 | D39: 24小时平直负荷，需量峰值最低，光伏与负荷叠合度较弱。

Sheet 测算
B1: 智能微电网经济评价 v3.3 · 介子九维 JIEZIJIUWEI
B2: 输入区（黄底蓝字单元格可修改；单元格批注含填报说明）
B3: 参数 | C3: 数值 | D3: 单位 | G3: 关键指标
B4: 场景选择 | G4: 全投资内部收益率（税前） | H4: =_zvfwiv
B5: 电价场景 | C5: 参考算例（代理购电·按需量） | G5: 全投资内部收益率（税后） | H5: =_z3ewnh | I5: 主评价指标
B6: =INDEX(_zkdmvf,MATCH(_zobook,_z3dy4z,0)) | G6: 资本金内部收益率 | H6: =_z2tbwe
B7: 典型日负荷形态 | C7: 白天生产型 | G7: 净现值（税后全投资） | H7: =_z8sr6o | I7: 万元
B8: =INDEX(_zt1gjv,MATCH(_zhoj8r,_z7qs7z,0)) | G8: 静态回收期 | H8: =_z3lcbu | I8: 年
G9: 动态回收期 | H9: =_z4kqsx | I9: 年
B10: A 投资造价 | G10: 度电成本 LCOE | H10: =_zehl1m | I10: 元/kWh
B11: 光伏单位造价 | C11: 3 | D11: 元/W | G11: 综合到户电价 | H11: =_zmbbnb | I11: 元/kWh
B12: 风电单位造价 | C12: 4.5 | D12: 元/W | G12: 年节省额（对照全量电网供电） | H12: =_zbx4ou | I12: 万元
B13: 储能单位造价 | C13: 1 | D13: 元/Wh | G13: 节省率 | H13: =_zisdds
B14: 柴发单位造价 | C14: 0.5 | D14: 元/W
B15: 充电桩投资 | C15: 300 | D15: 万元 | G15: 合规参考（就近就地消纳与可再生占比）
B16: 配电工程等其他投资 | C16: 800 | D16: 万元 | G16: 自用/可用发电量 ≥60% | H16: =_zq9jto | I16: =IF(_zq9jto>=0.6,"满足","不满足")
B17: 其他电源投资 | C17: 0 | D17: 万元 | G17: 可再生装机占比 ≥50% | H17: =_z4zxd3 | I17: =IF(_z4zxd3>=0.5,"满足","不满足")
G18: 自用/年用电量 ≥30% | H18: =_z31n7i | I18: =IF(_z31n7i>=0.3,"满足","不满足")
B19: B 运行参数
B20: 年出力衰减率 | C20: 0.005 | D20: % | G20: 首年电量、费用与收益构成（所选场景）
B21: 储能更换年份 | C21: 12 | D21: 第N年 | G21: 年可用发电量（万kWh） | H21: =_z39asj
B22: 更换费用比例 | C22: 0.5 | D22: % | G22: 年自发自用电量（万kWh） | H22: =_zdj37c
B23: 运维费率 | C23: 0.015 | D23: % | G23: 年余电上网电量（万kWh） | H23: =_zv9i5q
B24: 保险费率 | C24: 0.0025 | D24: % | G24: 年下网购电量（万kWh） | H24: =_zbr0hi
B25: 土地/场地租金（不含税） | C25: 0 | D25: 万元/年 | G25: 柴发年发电量（万kWh） | H25: =_zy2ig8
G26: 储能年放电量（万kWh） | H26: =_z0ernh
B27: C 融资与税务 | G27: 储能年谷时充电量（万kWh） | H27: =_zhfuoj
B28: 资本金比例 | C28: 0.3 | D28: % | G28: 年总用电量（万kWh） | H28: =_zpjfi7
B29: 贷款利率 | C29: 0.045 | D29: % | G29: 年购电电度费（万元） | H29: =_z8pux7
B30: 贷款年限 | C30: 15 | D30: 年 | G30: 年需量（容量）电费（万元） | H30: =_zzcemp
B31: 运营期 | C31: 25 | D31: 年 | G31: 年就近消纳输配电费（万元） | H31: =_zpo09w
B32: 折旧年限 | C32: 20 | D32: 年 | G32: 年政府性基金及附加（万元） | H32: =_z6l4ri
B33: 残值率 | C33: 0.05 | D33: % | G33: 柴发年燃料成本（万元） | H33: =_zdd3mz
B34: 所得税率 | C34: 0.25 | D34: % | G34: 其他电源年成本（万元） | H34: =_z2y4dt
B35: 所得税三免三减半 | C35: 否 | G35: 年综合用电成本（万元） | H35: =_zmkp8w
B36: 可抵扣进项税比例 | C36: 0.1 | D36: % | G36: 综合到户电价（元/kWh） | H36: =_zmbbnb
B37: 基准折现率 | C37: 0.06 | D37: % | G37: 全量电网供电对照成本（万元） | H37: =_z3wzt4
G38: 年节省额（万元） | H38: =_zbx4ou
B39: =IF(_z9rhi7>25,"运营期超过25年上限：年度现金流表最长25年，当前结果不完整，请修改运营期或用介子九维小程序测算","") | G39: 节省率 | H39: =_zisdds
G40: ① 自发自用节省（万元） | H40: =_zgk3lw
G41: ② 峰谷套利（万元） | H41: =_zriby8
G42: ③ 需量优化（万元） | H42: =_zbpwff
G43: ④ 余电上网（万元） | H43: =_z7m6d8
G44: ⑤ 需求响应（万元） | H44: =_ziv1gc
G45: ⑥ 充电桩服务费（万元） | H45: =_zz1w2z
G46: ⑦ 环境价值（单列，万元） | H46: =_zq1zhk
G47: 自用/可用发电量 | H47: =_zq9jto
G48: 自用/年用电量 | H48: =_z31n7i
G49: 可再生装机占比 | H49: =_z4zxd3
G51: 投资构成
G52: 光伏投资 | H52: =_zkh06o | I52: 万元
G53: 风电投资 | H53: =_z517d3 | I53: 万元
G54: 储能投资 | H54: =_z4p8is | I54: 万元
G55: 柴发投资 | H55: =_zka9am | I55: 万元
G56: 充电桩投资 | H56: =_zh76h3 | I56: 万元
G57: 配电工程等其他投资 | H57: =_zcyms1 | I57: 万元
G58: 其他电源投资 | H58: =_zghrhb | I58: 万元
G59: 总投资 | H59: =_z1tt59 | I59: 万元
G60: 资本金 | H60: =_zn0hoh | I60: 万元
G61: 贷款 | H61: =_zmqr32 | I61: 万元
G63: 综合到户电价对比（元/kWh）
G64: 微电网综合到户电价 | H64: =_zmbbnb | I64: 元/kWh
G65: 全量电网供电对照价 | H65: =IF(_zpjfi7>0,_z3wzt4/_zpjfi7,0) | I65: 元/kWh
B68: 逐年现金流（万元）
B69: 年份 | C69: 年收益合计（扣燃料成本） | D69: 运维保险及租金 | E69: 实缴增值税 | F69: 附加税费 | G69: 更换支出 | H69: 期末回收 | I69: 所得税（全投资） | J69: 税后全投资净现金流 | K69: 累计 | L69: 资本金净现金流
B70: 0 | C70: ='_引擎'!E64 | D70: 0 | E70: ='_引擎'!M64 | F70: ='_引擎'!O64 | G70: ='_引擎'!F64 | H70: ='_引擎'!AQ64 | I70: ='_引擎'!AG64 | J70: ='_引擎'!AS64 | K70: ='_引擎'!AU64 | L70: ='_引擎'!AT64
B71: 1 | C71: ='_引擎'!E65 | D71: =IF('_引擎'!B65,_zkfhzg,0) | E71: ='_引擎'!M65 | F71: ='_引擎'!O65 | G71: ='_引擎'!F65 | H71: ='_引擎'!AQ65 | I71: ='_引擎'!AG65 | J71: ='_引擎'!AS65 | K71: ='_引擎'!AU65 | L71: ='_引擎'!AT65
B72: 2 | C72: ='_引擎'!E66 | D72: =IF('_引擎'!B66,_zkfhzg,0) | E72: ='_引擎'!M66 | F72: ='_引擎'!O66 | G72: ='_引擎'!F66 | H72: ='_引擎'!AQ66 | I72: ='_引擎'!AG66 | J72: ='_引擎'!AS66 | K72: ='_引擎'!AU66 | L72: ='_引擎'!AT66
B73: 3 | C73: ='_引擎'!E67 | D73: =IF('_引擎'!B67,_zkfhzg,0) | E73: ='_引擎'!M67 | F73: ='_引擎'!O67 | G73: ='_引擎'!F67 | H73: ='_引擎'!AQ67 | I73: ='_引擎'!AG67 | J73: ='_引擎'!AS67 | K73: ='_引擎'!AU67 | L73: ='_引擎'!AT67
B74: 4 | C74: ='_引擎'!E68 | D74: =IF('_引擎'!B68,_zkfhzg,0) | E74: ='_引擎'!M68 | F74: ='_引擎'!O68 | G74: ='_引擎'!F68 | H74: ='_引擎'!AQ68 | I74: ='_引擎'!AG68 | J74: ='_引擎'!AS68 | K74: ='_引擎'!AU68 | L74: ='_引擎'!AT68
B75: 5 | C75: ='_引擎'!E69 | D75: =IF('_引擎'!B69,_zkfhzg,0) | E75: ='_引擎'!M69 | F75: ='_引擎'!O69 | G75: ='_引擎'!F69 | H75: ='_引擎'!AQ69 | I75: ='_引擎'!AG69 | J75: ='_引擎'!AS69 | K75: ='_引擎'!AU69 | L75: ='_引擎'!AT69
B76: 6 | C76: ='_引擎'!E70 | D76: =IF('_引擎'!B70,_zkfhzg,0) | E76: ='_引擎'!M70 | F76: ='_引擎'!O70 | G76: ='_引擎'!F70 | H76: ='_引擎'!AQ70 | I76: ='_引擎'!AG70 | J76: ='_引擎'!AS70 | K76: ='_引擎'!AU70 | L76: ='_引擎'!AT70
B77: 7 | C77: ='_引擎'!E71 | D77: =IF('_引擎'!B71,_zkfhzg,0) | E77: ='_引擎'!M71 | F77: ='_引擎'!O71 | G77: ='_引擎'!F71 | H77: ='_引擎'!AQ71 | I77: ='_引擎'!AG71 | J77: ='_引擎'!AS71 | K77: ='_引擎'!AU71 | L77: ='_引擎'!AT71
B78: 8 | C78: ='_引擎'!E72 | D78: =IF('_引擎'!B72,_zkfhzg,0) | E78: ='_引擎'!M72 | F78: ='_引擎'!O72 | G78: ='_引擎'!F72 | H78: ='_引擎'!AQ72 | I78: ='_引擎'!AG72 | J78: ='_引擎'!AS72 | K78: ='_引擎'!AU72 | L78: ='_引擎'!AT72
B79: 9 | C79: ='_引擎'!E73 | D79: =IF('_引擎'!B73,_zkfhzg,0) | E79: ='_引擎'!M73 | F79: ='_引擎'!O73 | G79: ='_引擎'!F73 | H79: ='_引擎'!AQ73 | I79: ='_引擎'!AG73 | J79: ='_引擎'!AS73 | K79: ='_引擎'!AU73 | L79: ='_引擎'!AT73
B80: 10 | C80: ='_引擎'!E74 | D80: =IF('_引擎'!B74,_zkfhzg,0) | E80: ='_引擎'!M74 | F80: ='_引擎'!O74 | G80: ='_引擎'!F74 | H80: ='_引擎'!AQ74 | I80: ='_引擎'!AG74 | J80: ='_引擎'!AS74 | K80: ='_引擎'!AU74 | L80: ='_引擎'!AT74
B81: 11 | C81: ='_引擎'!E75 | D81: =IF('_引擎'!B75,_zkfhzg,0) | E81: ='_引擎'!M75 | F81: ='_引擎'!O75 | G81: ='_引擎'!F75 | H81: ='_引擎'!AQ75 | I81: ='_引擎'!AG75 | J81: ='_引擎'!AS75 | K81: ='_引擎'!AU75 | L81: ='_引擎'!AT75
B82: 12 | C82: ='_引擎'!E76 | D82: =IF('_引擎'!B76,_zkfhzg,0) | E82: ='_引擎'!M76 | F82: ='_引擎'!O76 | G82: ='_引擎'!F76 | H82: ='_引擎'!AQ76 | I82: ='_引擎'!AG76 | J82: ='_引擎'!AS76 | K82: ='_引擎'!AU76 | L82: ='_引擎'!AT76
... B95: 25 | C95: ='_引擎'!E89 | D95: =IF('_引擎'!B89,_zkfhzg,0) | E95: ='_引擎'!M89 | F95: ='_引擎'!O89 | G95: ='_引擎'!F89 | H95: ='_引擎'!AQ89 | I95: ='_引擎'!AG89 | J95: ='_引擎'!AS89 | K95: ='_引擎'!AU89 | L95: ='_引擎'!AT89

Sheet _引擎
A1: 标量（引擎口径 2026-07；勿改）
A2: 电价场景序号 | B2: =MATCH(_zobook,_z3dy4z,0)
A3: 负荷形态序号 | B3: =MATCH(_zhoj8r,_z7qs7z,0)
A4: 组合列号 | B4: =(_zy5ipr-1)*3+_zflqft
A5: s_gen_avail | B5: =INDEX(_zs8gul,_zx9tbe)
A6: s_self_use | B6: =INDEX(_z7rtb0,_zx9tbe)
A7: s_export | B7: =INDEX(_zx3hze,_zx9tbe)
A8: s_purchase | B8: =INDEX(_zg5rek,_zx9tbe)
A9: s_diesel_q | B9: =INDEX(_zvd8oo,_zx9tbe)
A10: s_ess_discharge | B10: =INDEX(_z8uul7,_zx9tbe)
A11: s_ess_charge_grid | B11: =INDEX(_zmd2n1,_zx9tbe)
A12: s_total_load | B12: =INDEX(_zrss8w,_zx9tbe)
A13: s_energy_cost | B13: =INDEX(_zxylnr,_zx9tbe)
A14: s_demand_fee | B14: =INDEX(_zcmix6,_zx9tbe)
A15: s_td_fee_1192 | B15: =INDEX(_zc9vmb,_zx9tbe)
A16: s_fund_fee_1192 | B16: =INDEX(_zmt7yq,_zx9tbe)
A17: s_dg_cost | B17: =INDEX(_zgrhmu,_zx9tbe)
A18: s_other_cost | B18: =INDEX(_z2124k,_zx9tbe)
A19: s_user_total | B19: =INDEX(_zqq9kl,_zx9tbe)
A20: s_user_avg_price | B20: =INDEX(_z24fjs,_zx9tbe)
A21: s_baseline | B21: =INDEX(_zziz19,_zx9tbe)
A22: s_saving | B22: =INDEX(_zg9g0j,_zx9tbe)
A23: s_saving_rate | B23: =INDEX(_zpq4om,_zx9tbe)
A24: s_rev_selfuse | B24: =INDEX(_zs2zbw,_zx9tbe)
A25: s_rev_arbitrage | B25: =INDEX(_zjyrt0,_zx9tbe)
A26: s_rev_demand_saving | B26: =INDEX(_zy9h20,_zx9tbe)
A27: s_rev_export | B27: =INDEX(_zvhtq5,_zx9tbe)
A28: s_rev_dr | B28: =INDEX(_z8a1yw,_zx9tbe)
A29: s_rev_ev | B29: =INDEX(_zw9i4c,_zx9tbe)
A30: s_green_avoid | B30: =INDEX(_z83gdf,_zx9tbe)
A31: s_ratio_self_of_gen | B31: =INDEX(_zrngfq,_zx9tbe)
A32: s_ratio_self_of_load | B32: =INDEX(_z34nes,_zx9tbe)
A33: s_re_capacity_share | B33: =INDEX(_zsyvua,_zx9tbe)
A34: s_pv_mw | B34: =INDEX(_ztu197,_zx9tbe)
A35: s_wind_mw | B35: =INDEX(_zdz3nh,_zx9tbe)
A36: s_ess_mw | B36: =INDEX(_z59qak,_zx9tbe)
A37: s_ess_mwh | B37: =INDEX(_z7g7nz,_zx9tbe)
A38: s_dg_mw | B38: =INDEX(_zuo7z3,_zx9tbe)
A39: capex_pv | B39: =_z35787*_zqeqjw*100
A40: capex_wind | B40: =_zm0jdo*_zzg0id*100
A41: capex_ess | B41: =_z9ck23*_zv2cfz*100
A42: capex_dg | B42: =_zaapf6*_zqixf0*100
A43: capex_total | B43: =_zkh06o+_z517d3+_z4p8is+_zka9am+_zh76h3+_zcyms1+_zghrhb
A44: holiday_share | B44: =IF(_z1tt59>0,(_zkh06o+_z517d3)/_z1tt59,0)
A45: n_years | B45: =ROUND(_z9rhi7,0)
A46: equity | B46: =_z1tt59*_zzd9na
A47: loan | B47: =_z1tt59-_zn0hoh
A48: loan_years_r | B48: =ROUND(_zx0gw6,0)
A49: pay | B49: =IF(_zks9j8=0,_zmqr32/_z2al7i,_zmqr32*_zks9j8/(1-(1+_zks9j8)^-_z2al7i))
A50: capex_net | B50: =_z1tt59*(1-_z2vg7y)
A51: vat_pool0 | B51: =_z1tt59*_z2vg7y
A52: dep_base | B52: =_zbb0h1*(1-_z1sub1)
A53: dep_years_tax | B53: =ROUND(_zva2xn,0)
A54: dep_years_eff | B54: =MIN(_zk7d33,_zx5hja)
A55: dep_annual | B55: =_zxo0o2/_zk7d33
A56: opex | B56: =_z1tt59*(_zfbc18+_zlghw4)+_zofnoh
A57: salvage_value | B57: =_zbb0h1*_z1sub1
A58: terminal_value | B58: =_z4gfqk+_zxo0o2*MAX(0,_zk7d33-_zx5hja)/_zk7d33
A59: replace_year_r | B59: =ROUND(_z75lzf,0)
A60: benefit_flat | B60: =_zriby8+_zbpwff+_ziv1gc+_zz1w2z
A63: 年份 | B63: 运营期内 | C63: 衰减系数 | D63: 衰减性收益 | E63: 毛收益 | F63: 更换支出 | G63: 更换进项税 | H63: 更换支出(不含税) | I63: 应税收入含税 | J63: 应税收入不含税 | K63: 销项税 | L63: 进项池期初 | M63: 实缴增值税 | N63: 进项池期末 | O63: 附加税费 | P63: 净收益不含税口径 | Q63: 期初贷款余额 | R63: 利息 | S63: 还本付息 | T63: 还本 | U63: 期末贷款余额 | V63: 折旧 | W63: 免减系数 | X63: 有效税率系数 | Y63: EBT全投资 | Z63: 亏损池A·1年 | AA63: 亏损池A·2年 | AB63: 亏损池A·3年 | AC63: 亏损池A·4年 | AD63: 亏损池A·5年 | AE63: 亏损池A·当年弥补 | AF63: 应税所得·全投资 | AG63: 所得税·全投资 | AH63: EBT资本金 | AI63: 亏损池E·1年 | AJ63: 亏损池E·2年 | AK63: 亏损池E·3年 | AL63: 亏损池E·4年 | AM63: 亏损池E·5年 | AN63: 亏损池E·当年弥补 | AO63: 应税所得·资本金 | AP63: 所得税·资本金 | AQ63: 期末回收 | AR63: 税前全投资净现金流 | AS63: 税后全投资净现金流 | AT63: 资本金净现金流 | AU63: 累计税后 | AV63: 转正标志 | AW63: 折现税后 | AX63: 累计折现 | AY63: 转正标志动态 | AZ63: 自产电量衰减后 | BA63: LCOE年成本 | BB63: 符号跟踪·税前 | BC63: 变号计数·税前 | BD63: 符号跟踪·税后 | BE63: 变号计数·税后 | BF63: 符号跟踪·资本金 | BG63: 变号计数·资本金
A64: 0 | B64: =FALSE | C64: 0 | D64: 0 | E64: 0 | F64: 0 | G64: 0 | H64: 0 | I64: 0 | J64: 0 | K64: 0 | L64: 0 | M64: 0 | N64: =_zh2s1v | O64: 0 | P64: 0 | Q64: 0 | R64: 0 | S64: 0 | T64: 0 | U64: =_zmqr32 | V64: 0 | W64: 0 | X64: 0 | Y64: 0 | Z64: 0 | AA64: 0 | AB64: 0 | AC64: 0 | AD64: 0 | AE64: 0 | AF64: 0 | AG64: 0 | AH64: 0 | AI64: 0 | AJ64: 0 | AK64: 0 | AL64: 0 | AM64: 0 | AN64: 0 | AO64: 0 | AP64: 0 | AQ64: 0 | AR64: =-_z1tt59 | AS64: =-_z1tt59 | AT64: =-_zn0hoh | AU64: =AS64 | AV64: 0 | AW64: =AS64 | AX64: =AW64 | AY64: 0 | AZ64: 0 | BA64: 0 | BB64: =SIGN(AR64) | BC64: 0 | BD64: =SIGN(AS64) | BE64: 0 | BF64: =SIGN(AT64) | BG64: 0
A65: 1 | B65: =AND(A65>=1,A65<=_zx5hja) | C65: =IF(B65,(1-_zecdlb)^(A65-1),0) | D65: =(_zgk3lw+_z7m6d8)*C65 | E65: =IF(B65,D65+_zmztd5-_zdd3mz-_z2y4dt,0) | F65: =IF(AND(B65,A65=_ztfkfy),_z4p8is*_zh30bl,0) | G65: =F65*0.13/(1+0.13) | H65: =F65-G65 | I65: =IF(B65,_z7m6d8*C65+_zz1w2z,0) | J65: =I65/(1+0.13) | K65: =I65-J65 | L65: =N64+G65 | M65: =MAX(0,K65-L65) | N65: =MAX(0,L65-K65) | O65: =M65*0.12 | P65: =E65-K65 | Q65: =U64 | R65: =IF(AND(B65,A65<=_z2al7i),Q65*_zks9j8,0) | S65: =IF(AND(B65,A65<=_z2al7i),_zgsfrl,0) | T65: =S65-R65 | U65: =MAX(0,Q65-T65) | V65: =IF(AND(B65,A65<=_zupe8l),_z0jo6h,0) | W65: =IF((_zlt415="是"),IF(A65<=3,0,IF(A65<=6,0.5,1)),1) | X65: =_zrzkf6*W65+(1-_zrzkf6) | Y65: =IF(B65,P65-_zkfhzg-O65-V65-H65,0) | Z65: =MAX(0,-Y64) | AA65: =MIN(Z64,MAX(0,(AD64+AC64+AB64+AA64+Z64)-AE64)) | AB65: =MIN(AA64,MAX(0,(AD64+AC64+AB64+AA64)-AE64)) | AC65: =MIN(AB64,MAX(0,(AD64+AC64+AB64)-AE64)) | AD65: =MIN(AC64,MAX(0,(AD64+AC64)-AE64)) | AE65: =MIN(MAX(Y65,0),Z65+AA65+AB65+AC65+AD65) | AF65: =MAX(Y65,0)-AE65 | AG65: =AF65*_zk03a3*X65 | AH65: =IF(B65,Y65-R65,0) | AI65: =MAX(0,-AH64) | AJ65: =MIN(AI64,MAX(0,(AM64+AL64+AK64+AJ64+AI64)-AN64)) | AK65: =MIN(AJ64,MAX(0,(AM64+AL64+AK64+AJ64)-AN64)) | AL65: =MIN(AK64,MAX(0,(AM64+AL64+AK64)-AN64)) | AM65: =MIN(AL64,MAX(0,(AM64+AL64)-AN64)) | AN65: =MIN(MAX(AH65,0),AI65+AJ65+AK65+AL65+AM65) | AO65: =MAX(AH65,0)-AN65 | AP65: =AO65*_zk03a3*X65 | AQ65: =IF(A65=_zx5hja,_zk1wd3,0) | AR65: =IF(B65,E65-_zkfhzg-M65-O65-F65+AQ65,0) | AS65: =AR65-AG65 | AT65: =IF(B65,E65-_zkfhzg-M65-O65-F65-S65-AP65+AQ65-IF(AND(A65=_zx5hja,_z2al7i>_zx5hja),U65,0),0) | AU65: =AU64+AS65 | AV65: =IF(AND(AU64<0,AU65>=0,AS65>0),1,0) | AW65: =AS65/(1+_z1ltt4)^A65 | AX65: =AX64+AW65 | AY65: =IF(AND(AX64<0,AX65>=0,AW65>0),1,0) | AZ65: =(_z39asj+_zy2ig8)*C65 | BA65: =IF(B65,_zkfhzg+_zdd3mz+_z2y4dt+F65-AQ65,0) | BB65: =IF(AR65=0,BB64,SIGN(AR65)) | BC65: =BC64+IF(OR(AR65=0,BB64=0),0,IF(SIGN(AR65)<>BB64,1,0)) | BD65: =IF(AS65=0,BD64,SIGN(AS65)) | BE65: =BE64+IF(OR(AS65=0,BD64=0),0,IF(SIGN(AS65)<>BD64,1,0)) | BF65: =IF(AT65=0,BF64,SIGN(AT65)) | BG65: =BG64+IF(OR(AT65=0,BF64=0),0,IF(SIGN(AT65)<>BF64,1,0))
A66: 2 | B66: =AND(A66>=1,A66<=_zx5hja) | C66: =IF(B66,(1-_zecdlb)^(A66-1),0) | D66: =(_zgk3lw+_z7m6d8)*C66 | E66: =IF(B66,D66+_zmztd5-_zdd3mz-_z2y4dt,0) | F66: =IF(AND(B66,A66=_ztfkfy),_z4p8is*_zh30bl,0) | G66: =F66*0.13/(1+0.13) | H66: =F66-G66 | I66: =IF(B66,_z7m6d8*C66+_zz1w2z,0) | J66: =I66/(1+0.13) | K66: =I66-J66 | L66: =N65+G66 | M66: =MAX(0,K66-L66) | N66: =MAX(0,L66-K66) | O66: =M66*0.12 | P66: =E66-K66 | Q66: =U65 | R66: =IF(AND(B66,A66<=_z2al7i),Q66*_zks9j8,0) | S66: =IF(AND(B66,A66<=_z2al7i),_zgsfrl,0) | T66: =S66-R66 | U66: =MAX(0,Q66-T66) | V66: =IF(AND(B66,A66<=_zupe8l),_z0jo6h,0) | W66: =IF((_zlt415="是"),IF(A66<=3,0,IF(A66<=6,0.5,1)),1) | X66: =_zrzkf6*W66+(1-_zrzkf6) | Y66: =IF(B66,P66-_zkfhzg-O66-V66-H66,0) | Z66: =MAX(0,-Y65) | AA66: =MIN(Z65,MAX(0,(AD65+AC65+AB65+AA65+Z65)-AE65)) | AB66: =MIN(AA65,MAX(0,(AD65+AC65+AB65+AA65)-AE65)) | AC66: =MIN(AB65,MAX(0,(AD65+AC65+AB65)-AE65)) | AD66: =MIN(AC65,MAX(0,(AD65+AC65)-AE65)) | AE66: =MIN(MAX(Y66,0),Z66+AA66+AB66+AC66+AD66) | AF66: =MAX(Y66,0)-AE66 | AG66: =AF66*_zk03a3*X66 | AH66: =IF(B66,Y66-R66,0) | AI66: =MAX(0,-AH65) | AJ66: =MIN(AI65,MAX(0,(AM65+AL65+AK65+AJ65+AI65)-AN65)) | AK66: =MIN(AJ65,MAX(0,(AM65+AL65+AK65+AJ65)-AN65)) | AL66: =MIN(AK65,MAX(0,(AM65+AL65+AK65)-AN65)) | AM66: =MIN(AL65,MAX(0,(AM65+AL65)-AN65)) | AN66: =MIN(MAX(AH66,0),AI66+AJ66+AK66+AL66+AM66) | AO66: =MAX(AH66,0)-AN66 | AP66: =AO66*_zk03a3*X66 | AQ66: =IF(A66=_zx5hja,_zk1wd3,0) | AR66: =IF(B66,E66-_zkfhzg-M66-O66-F66+AQ66,0) | AS66: =AR66-AG66 | AT66: =IF(B66,E66-_zkfhzg-M66-O66-F66-S66-AP66+AQ66-IF(AND(A66=_zx5hja,_z2al7i>_zx5hja),U66,0),0) | AU66: =AU65+AS66 | AV66: =IF(AND(AU65<0,AU66>=0,AS66>0),1,0) | AW66: =AS66/(1+_z1ltt4)^A66 | AX66: =AX65+AW66 | AY66: =IF(AND(AX65<0,AX66>=0,AW66>0),1,0) | AZ66: =(_z39asj+_zy2ig8)*C66 | BA66: =IF(B66,_zkfhzg+_zdd3mz+_z2y4dt+F66-AQ66,0) | BB66: =IF(AR66=0,BB65,SIGN(AR66)) | BC66: =BC65+IF(OR(AR66=0,BB65=0),0,IF(SIGN(AR66)<>BB65,1,0)) | BD66: =IF(AS66=0,BD65,SIGN(AS66)) | BE66: =BE65+IF(OR(AS66=0,BD65=0),0,IF(SIGN(AS66)<>BD65,1,0)) | BF66: =IF(AT66=0,BF65,SIGN(AT66)) | BG66: =BG65+IF(OR(AT66=0,BF65=0),0,IF(SIGN(AT66)<>BF65,1,0))
A67: 3 | B67: =AND(A67>=1,A67<=_zx5hja) | C67: =IF(B67,(1-_zecdlb)^(A67-1),0) | D67: =(_zgk3lw+_z7m6d8)*C67 | E67: =IF(B67,D67+_zmztd5-_zdd3mz-_z2y4dt,0) | F67: =IF(AND(B67,A67=_ztfkfy),_z4p8is*_zh30bl,0) | G67: =F67*0.13/(1+0.13) | H67: =F67-G67 | I67: =IF(B67,_z7m6d8*C67+_zz1w2z,0) | J67: =I67/(1+0.13) | K67: =I67-J67 | L67: =N66+G67 | M67: =MAX(0,K67-L67) | N67: =MAX(0,L67-K67) | O67: =M67*0.12 | P67: =E67-K67 | Q67: =U66 | R67: =IF(AND(B67,A67<=_z2al7i),Q67*_zks9j8,0) | S67: =IF(AND(B67,A67<=_z2al7i),_zgsfrl,0) | T67: =S67-R67 | U67: =MAX(0,Q67-T67) | V67: =IF(AND(B67,A67<=_zupe8l),_z0jo6h,0) | W67: =IF((_zlt415="是"),IF(A67<=3,0,IF(A67<=6,0.5,1)),1) | X67: =_zrzkf6*W67+(1-_zrzkf6) | Y67: =IF(B67,P67-_zkfhzg-O67-V67-H67,0) | Z67: =MAX(0,-Y66) | AA67: =MIN(Z66,MAX(0,(AD66+AC66+AB66+AA66+Z66)-AE66)) | AB67: =MIN(AA66,MAX(0,(AD66+AC66+AB66+AA66)-AE66)) | AC67: =MIN(AB66,MAX(0,(AD66+AC66+AB66)-AE66)) | AD67: =MIN(AC66,MAX(0,(AD66+AC66)-AE66)) | AE67: =MIN(MAX(Y67,0),Z67+AA67+AB67+AC67+AD67) | AF67: =MAX(Y67,0)-AE67 | AG67: =AF67*_zk03a3*X67 | AH67: =IF(B67,Y67-R67,0) | AI67: =MAX(0,-AH66) | AJ67: =MIN(AI66,MAX(0,(AM66+AL66+AK66+AJ66+AI66)-AN66)) | AK67: =MIN(AJ66,MAX(0,(AM66+AL66+AK66+AJ66)-AN66)) | AL67: =MIN(AK66,MAX(0,(AM66+AL66+AK66)-AN66)) | AM67: =MIN(AL66,MAX(0,(AM66+AL66)-AN66)) | AN67: =MIN(MAX(AH67,0),AI67+AJ67+AK67+AL67+AM67) | AO67: =MAX(AH67,0)-AN67 | AP67: =AO67*_zk03a3*X67 | AQ67: =IF(A67=_zx5hja,_zk1wd3,0) | AR67: =IF(B67,E67-_zkfhzg-M67-O67-F67+AQ67,0) | AS67: =AR67-AG67 | AT67: =IF(B67,E67-_zkfhzg-M67-O67-F67-S67-AP67+AQ67-IF(AND(A67=_zx5hja,_z2al7i>_zx5hja),U67,0),0) | AU67: =AU66+AS67 | AV67: =IF(AND(AU66<0,AU67>=0,AS67>0),1,0) | AW67: =AS67/(1+_z1ltt4)^A67 | AX67: =AX66+AW67 | AY67: =IF(AND(AX66<0,AX67>=0,AW67>0),1,0) | AZ67: =(_z39asj+_zy2ig8)*C67 | BA67: =IF(B67,_zkfhzg+_zdd3mz+_z2y4dt+F67-AQ67,0) | BB67: =IF(AR67=0,BB66,SIGN(AR67)) | BC67: =BC66+IF(OR(AR67=0,BB66=0),0,IF(SIGN(AR67)<>BB66,1,0)) | BD67: =IF(AS67=0,BD66,SIGN(AS67)) | BE67: =BE66+IF(OR(AS67=0,BD66=0),0,IF(SIGN(AS67)<>BD66,1,0)) | BF67: =IF(AT67=0,BF66,SIGN(AT67)) | BG67: =BG66+IF(OR(AT67=0,BF66=0),0,IF(SIGN(AT67)<>BF66,1,0))
A68: 4 | B68: =AND(A68>=1,A68<=_zx5hja) | C68: =IF(B68,(1-_zecdlb)^(A68-1),0) | D68: =(_zgk3lw+_z7m6d8)*C68 | E68: =IF(B68,D68+_zmztd5-_zdd3mz-_z2y4dt,0) | F68: =IF(AND(B68,A68=_ztfkfy),_z4p8is*_zh30bl,0) | G68: =F68*0.13/(1+0.13) | H68: =F68-G68 | I68: =IF(B68,_z7m6d8*C68+_zz1w2z,0) | J68: =I68/(1+0.13) | K68: =I68-J68 | L68: =N67+G68 | M68: =MAX(0,K68-L68) | N68: =MAX(0,L68-K68) | O68: =M68*0.12 | P68: =E68-K68 | Q68: =U67 | R68: =IF(AND(B68,A68<=_z2al7i),Q68*_zks9j8,0) | S68: =IF(AND(B68,A68<=_z2al7i),_zgsfrl,0) | T68: =S68-R68 | U68: =MAX(0,Q68-T68) | V68: =IF(AND(B68,A68<=_zupe8l),_z0jo6h,0) | W68: =IF((_zlt415="是"),IF(A68<=3,0,IF(A68<=6,0.5,1)),1) | X68: =_zrzkf6*W68+(1-_zrzkf6) | Y68: =IF(B68,P68-_zkfhzg-O68-V68-H68,0) | Z68: =MAX(0,-Y67) | AA68: =MIN(Z67,MAX(0,(AD67+AC67+AB67+AA67+Z67)-AE67)) | AB68: =MIN(AA67,MAX(0,(AD67+AC67+AB67+AA67)-AE67)) | AC68: =MIN(AB67,MAX(0,(AD67+AC67+AB67)-AE67)) | AD68: =MIN(AC67,MAX(0,(AD67+AC67)-AE67)) | AE68: =MIN(MAX(Y68,0),Z68+AA68+AB68+AC68+AD68) | AF68: =MAX(Y68,0)-AE68 | AG68: =AF68*_zk03a3*X68 | AH68: =IF(B68,Y68-R68,0) | AI68: =MAX(0,-AH67) | AJ68: =MIN(AI67,MAX(0,(AM67+AL67+AK67+AJ67+AI67)-AN67)) | AK68: =MIN(AJ67,MAX(0,(AM67+AL67+AK67+AJ67)-AN67)) | AL68: =MIN(AK67,MAX(0,(AM67+AL67+AK67)-AN67)) | AM68: =MIN(AL67,MAX(0,(AM67+AL67)-AN67)) | AN68: =MIN(MAX(AH68,0),AI68+AJ68+AK68+AL68+AM68) | AO68: =MAX(AH68,0)-AN68 | AP68: =AO68*_zk03a3*X68 | AQ68: =IF(A68=_zx5hja,_zk1wd3,0) | AR68: =IF(B68,E68-_zkfhzg-M68-O68-F68+AQ68,0) | AS68: =AR68-AG68 | AT68: =IF(B68,E68-_zkfhzg-M68-O68-F68-S68-AP68+AQ68-IF(AND(A68=_zx5hja,_z2al7i>_zx5hja),U68,0),0) | AU68: =AU67+AS68 | AV68: =IF(AND(AU67<0,AU68>=0,AS68>0),1,0) | AW68: =AS68/(1+_z1ltt4)^A68 | AX68: =AX67+AW68 | AY68: =IF(AND(AX67<0,AX68>=0,AW68>0),1,0) | AZ68: =(_z39asj+_zy2ig8)*C68 | BA68: =IF(B68,_zkfhzg+_zdd3mz+_z2y4dt+F68-AQ68,0) | BB68: =IF(AR68=0,BB67,SIGN(AR68)) | BC68: =BC67+IF(OR(AR68=0,BB67=0),0,IF(SIGN(AR68)<>BB67,1,0)) | BD68: =IF(AS68=0,BD67,SIGN(AS68)) | BE68: =BE67+IF(OR(AS68=0,BD67=0),0,IF(SIGN(AS68)<>BD67,1,0)) | BF68: =IF(AT68=0,BF67,SIGN(AT68)) | BG68: =BG67+IF(OR(AT68=0,BF67=0),0,IF(SIGN(AT68)<>BF67,1,0))
A69: 5 | B69: =AND(A69>=1,A69<=_zx5hja) | C69: =IF(B69,(1-_zecdlb)^(A69-1),0) | D69: =(_zgk3lw+_z7m6d8)*C69 | E69: =IF(B69,D69+_zmztd5-_zdd3mz-_z2y4dt,0) | F69: =IF(AND(B69,A69=_ztfkfy),_z4p8is*_zh30bl,0) | G69: =F69*0.13/(1+0.13) | H69: =F69-G69 | I69: =IF(B69,_z7m6d8*C69+_zz1w2z,0) | J69: =I69/(1+0.13) | K69: =I69-J69 | L69: =N68+G69 | M69: =MAX(0,K69-L69) | N69: =MAX(0,L69-K69) | O69: =M69*0.12 | P69: =E69-K69 | Q69: =U68 | R69: =IF(AND(B69,A69<=_z2al7i),Q69*_zks9j8,0) | S69: =IF(AND(B69,A69<=_z2al7i),_zgsfrl,0) | T69: =S69-R69 | U69: =MAX(0,Q69-T69) | V69: =IF(AND(B69,A69<=_zupe8l),_z0jo6h,0) | W69: =IF((_zlt415="是"),IF(A69<=3,0,IF(A69<=6,0.5,1)),1) | X69: =_zrzkf6*W69+(1-_zrzkf6) | Y69: =IF(B69,P69-_zkfhzg-O69-V69-H69,0) | Z69: =MAX(0,-Y68) | AA69: =MIN(Z68,MAX(0,(AD68+AC68+AB68+AA68+Z68)-AE68)) | AB69: =MIN(AA68,MAX(0,(AD68+AC68+AB68+AA68)-AE68)) | AC69: =MIN(AB68,MAX(0,(AD68+AC68+AB68)-AE68)) | AD69: =MIN(AC68,MAX(0,(AD68+AC68)-AE68)) | AE69: =MIN(MAX(Y69,0),Z69+AA69+AB69+AC69+AD69) | AF69: =MAX(Y69,0)-AE69 | AG69: =AF69*_zk03a3*X69 | AH69: =IF(B69,Y69-R69,0) | AI69: =MAX(0,-AH68) | AJ69: =MIN(AI68,MAX(0,(AM68+AL68+AK68+AJ68+AI68)-AN68)) | AK69: =MIN(AJ68,MAX(0,(AM68+AL68+AK68+AJ68)-AN68)) | AL69: =MIN(AK68,MAX(0,(AM68+AL68+AK68)-AN68)) | AM69: =MIN(AL68,MAX(0,(AM68+AL68)-AN68)) | AN69: =MIN(MAX(AH69,0),AI69+AJ69+AK69+AL69+AM69) | AO69: =MAX(AH69,0)-AN69 | AP69: =AO69*_zk03a3*X69 | AQ69: =IF(A69=_zx5hja,_zk1wd3,0) | AR69: =IF(B69,E69-_zkfhzg-M69-O69-F69+AQ69,0) | AS69: =AR69-AG69 | AT69: =IF(B69,E69-_zkfhzg-M69-O69-F69-S69-AP69+AQ69-IF(AND(A69=_zx5hja,_z2al7i>_zx5hja),U69,0),0) | AU69: =AU68+AS69 | AV69: =IF(AND(AU68<0,AU69>=0,AS69>0),1,0) | AW69: =AS69/(1+_z1ltt4)^A69 | AX69: =AX68+AW69 | AY69: =IF(AND(AX68<0,AX69>=0,AW69>0),1,0) | AZ69: =(_z39asj+_zy2ig8)*C69 | BA69: =IF(B69,_zkfhzg+_zdd3mz+_z2y4dt+F69-AQ69,0) | BB69: =IF(AR69=0,BB68,SIGN(AR69)) | BC69: =BC68+IF(OR(AR69=0,BB68=0),0,IF(SIGN(AR69)<>BB68,1,0)) | BD69: =IF(AS69=0,BD68,SIGN(AS69)) | BE69: =BE68+IF(OR(AS69=0,BD68=0),0,IF(SIGN(AS69)<>BD68,1,0)) | BF69: =IF(AT69=0,BF68,SIGN(AT69)) | BG69: =BG68+IF(OR(AT69=0,BF68=0),0,IF(SIGN(AT69)<>BF68,1,0))
A70: 6 | B70: =AND(A70>=1,A70<=_zx5hja) | C70: =IF(B70,(1-_zecdlb)^(A70-1),0) | D70: =(_zgk3lw+_z7m6d8)*C70 | E70: =IF(B70,D70+_zmztd5-_zdd3mz-_z2y4dt,0) | F70: =IF(AND(B70,A70=_ztfkfy),_z4p8is*_zh30bl,0) | G70: =F70*0.13/(1+0.13) | H70: =F70-G70 | I70: =IF(B70,_z7m6d8*C70+_zz1w2z,0) | J70: =I70/(1+0.13) | K70: =I70-J70 | L70: =N69+G70 | M70: =MAX(0,K70-L70) | N70: =MAX(0,L70-K70) | O70: =M70*0.12 | P70: =E70-K70 | Q70: =U69 | R70: =IF(AND(B70,A70<=_z2al7i),Q70*_zks9j8,0) | S70: =IF(AND(B70,A70<=_z2al7i),_zgsfrl,0) | T70: =S70-R70 | U70: =MAX(0,Q70-T70) | V70: =IF(AND(B70,A70<=_zupe8l),_z0jo6h,0) | W70: =IF((_zlt415="是"),IF(A70<=3,0,IF(A70<=6,0.5,1)),1) | X70: =_zrzkf6*W70+(1-_zrzkf6) | Y70: =IF(B70,P70-_zkfhzg-O70-V70-H70,0) | Z70: =MAX(0,-Y69) | AA70: =MIN(Z69,MAX(0,(AD69+AC69+AB69+AA69+Z69)-AE69)) | AB70: =MIN(AA69,MAX(0,(AD69+AC69+AB69+AA69)-AE69)) | AC70: =MIN(AB69,MAX(0,(AD69+AC69+AB69)-AE69)) | AD70: =MIN(AC69,MAX(0,(AD69+AC69)-AE69)) | AE70: =MIN(MAX(Y70,0),Z70+AA70+AB70+AC70+AD70) | AF70: =MAX(Y70,0)-AE70 | AG70: =AF70*_zk03a3*X70 | AH70: =IF(B70,Y70-R70,0) | AI70: =MAX(0,-AH69) | AJ70: =MIN(AI69,MAX(0,(AM69+AL69+AK69+AJ69+AI69)-AN69)) | AK70: =MIN(AJ69,MAX(0,(AM69+AL69+AK69+AJ69)-AN69)) | AL70: =MIN(AK69,MAX(0,(AM69+AL69+AK69)-AN69)) | AM70: =MIN(AL69,MAX(0,(AM69+AL69)-AN69)) | AN70: =MIN(MAX(AH70,0),AI70+AJ70+AK70+AL70+AM70) | AO70: =MAX(AH70,0)-AN70 | AP70: =AO70*_zk03a3*X70 | AQ70: =IF(A70=_zx5hja,_zk1wd3,0) | AR70: =IF(B70,E70-_zkfhzg-M70-O70-F70+AQ70,0) | AS70: =AR70-AG70 | AT70: =IF(B70,E70-_zkfhzg-M70-O70-F70-S70-AP70+AQ70-IF(AND(A70=_zx5hja,_z2al7i>_zx5hja),U70,0),0) | AU70: =AU69+AS70 | AV70: =IF(AND(AU69<0,AU70>=0,AS70>0),1,0) | AW70: =AS70/(1+_z1ltt4)^A70 | AX70: =AX69+AW70 | AY70: =IF(AND(AX69<0,AX70>=0,AW70>0),1,0) | AZ70: =(_z39asj+_zy2ig8)*C70 | BA70: =IF(B70,_zkfhzg+_zdd3mz+_z2y4dt+F70-AQ70,0) | BB70: =IF(AR70=0,BB69,SIGN(AR70)) | BC70: =BC69+IF(OR(AR70=0,BB69=0),0,IF(SIGN(AR70)<>BB69,1,0)) | BD70: =IF(AS70=0,BD69,SIGN(AS70)) | BE70: =BE69+IF(OR(AS70=0,BD69=0),0,IF(SIGN(AS70)<>BD69,1,0)) | BF70: =IF(AT70=0,BF69,SIGN(AT70)) | BG70: =BG69+IF(OR(AT70=0,BF69=0),0,IF(SIGN(AT70)<>BF69,1,0))
A71: 7 | B71: =AND(A71>=1,A71<=_zx5hja) | C71: =IF(B71,(1-_zecdlb)^(A71-1),0) | D71: =(_zgk3lw+_z7m6d8)*C71 | E71: =IF(B71,D71+_zmztd5-_zdd3mz-_z2y4dt,0) | F71: =IF(AND(B71,A71=_ztfkfy),_z4p8is*_zh30bl,0) | G71: =F71*0.13/(1+0.13) | H71: =F71-G71 | I71: =IF(B71,_z7m6d8*C71+_zz1w2z,0) | J71: =I71/(1+0.13) | K71: =I71-J71 | L71: =N70+G71 | M71: =MAX(0,K71-L71) | N71: =MAX(0,L71-K71) | O71: =M71*0.12 | P71: =E71-K71 | Q71: =U70 | R71: =IF(AND(B71,A71<=_z2al7i),Q71*_zks9j8,0) | S71: =IF(AND(B71,A71<=_z2al7i),_zgsfrl,0) | T71: =S71-R71 | U71: =MAX(0,Q71-T71) | V71: =IF(AND(B71,A71<=_zupe8l),_z0jo6h,0) | W71: =IF((_zlt415="是"),IF(A71<=3,0,IF(A71<=6,0.5,1)),1) | X71: =_zrzkf6*W71+(1-_zrzkf6) | Y71: =IF(B71,P71-_zkfhzg-O71-V71-H71,0) | Z71: =MAX(0,-Y70) | AA71: =MIN(Z70,MAX(0,(AD70+AC70+AB70+AA70+Z70)-AE70)) | AB71: =MIN(AA70,MAX(0,(AD70+AC70+AB70+AA70)-AE70)) | AC71: =MIN(AB70,MAX(0,(AD70+AC70+AB70)-AE70)) | AD71: =MIN(AC70,MAX(0,(AD70+AC70)-AE70)) | AE71: =MIN(MAX(Y71,0),Z71+AA71+AB71+AC71+AD71) | AF71: =MAX(Y71,0)-AE71 | AG71: =AF71*_zk03a3*X71 | AH71: =IF(B71,Y71-R71,0) | AI71: =MAX(0,-AH70) | AJ71: =MIN(AI70,MAX(0,(AM70+AL70+AK70+AJ70+AI70)-AN70)) | AK71: =MIN(AJ70,MAX(0,(AM70+AL70+AK70+AJ70)-AN70)) | AL71: =MIN(AK70,MAX(0,(AM70+AL70+AK70)-AN70)) | AM71: =MIN(AL70,MAX(0,(AM70+AL70)-AN70)) | AN71: =MIN(MAX(AH71,0),AI71+AJ71+AK71+AL71+AM71) | AO71: =MAX(AH71,0)-AN71 | AP71: =AO71*_zk03a3*X71 | AQ71: =IF(A71=_zx5hja,_zk1wd3,0) | AR71: =IF(B71,E71-_zkfhzg-M71-O71-F71+AQ71,0) | AS71: =AR71-AG71 | AT71: =IF(B71,E71-_zkfhzg-M71-O71-F71-S71-AP71+AQ71-IF(AND(A71=_zx5hja,_z2al7i>_zx5hja),U71,0),0) | AU71: =AU70+AS71 | AV71: =IF(AND(AU70<0,AU71>=0,AS71>0),1,0) | AW71: =AS71/(1+_z1ltt4)^A71 | AX71: =AX70+AW71 | AY71: =IF(AND(AX70<0,AX71>=0,AW71>0),1,0) | AZ71: =(_z39asj+_zy2ig8)*C71 | BA71: =IF(B71,_zkfhzg+_zdd3mz+_z2y4dt+F71-AQ71,0) | BB71: =IF(AR71=0,BB70,SIGN(AR71)) | BC71: =BC70+IF(OR(AR71=0,BB70=0),0,IF(SIGN(AR71)<>BB70,1,0)) | BD71: =IF(AS71=0,BD70,SIGN(AS71)) | BE71: =BE70+IF(OR(AS71=0,BD70=0),0,IF(SIGN(AS71)<>BD70,1,0)) | BF71: =IF(AT71=0,BF70,SIGN(AT71)) | BG71: =BG70+IF(OR(AT71=0,BF70=0),0,IF(SIGN(AT71)<>BF70,1,0))
A72: 8 | B72: =AND(A72>=1,A72<=_zx5hja) | C72: =IF(B72,(1-_zecdlb)^(A72-1),0) | D72: =(_zgk3lw+_z7m6d8)*C72 | E72: =IF(B72,D72+_zmztd5-_zdd3mz-_z2y4dt,0) | F72: =IF(AND(B72,A72=_ztfkfy),_z4p8is*_zh30bl,0) | G72: =F72*0.13/(1+0.13) | H72: =F72-G72 | I72: =IF(B72,_z7m6d8*C72+_zz1w2z,0) | J72: =I72/(1+0.13) | K72: =I72-J72 | L72: =N71+G72 | M72: =MAX(0,K72-L72) | N72: =MAX(0,L72-K72) | O72: =M72*0.12 | P72: =E72-K72 | Q72: =U71 | R72: =IF(AND(B72,A72<=_z2al7i),Q72*_zks9j8,0) | S72: =IF(AND(B72,A72<=_z2al7i),_zgsfrl,0) | T72: =S72-R72 | U72: =MAX(0,Q72-T72) | V72: =IF(AND(B72,A72<=_zupe8l),_z0jo6h,0) | W72: =IF((_zlt415="是"),IF(A72<=3,0,IF(A72<=6,0.5,1)),1) | X72: =_zrzkf6*W72+(1-_zrzkf6) | Y72: =IF(B72,P72-_zkfhzg-O72-V72-H72,0) | Z72: =MAX(0,-Y71) | AA72: =MIN(Z71,MAX(0,(AD71+AC71+AB71+AA71+Z71)-AE71)) | AB72: =MIN(AA71,MAX(0,(AD71+AC71+AB71+AA71)-AE71)) | AC72: =MIN(AB71,MAX(0,(AD71+AC71+AB71)-AE71)) | AD72: =MIN(AC71,MAX(0,(AD71+AC71)-AE71)) | AE72: =MIN(MAX(Y72,0),Z72+AA72+AB72+AC72+AD72) | AF72: =MAX(Y72,0)-AE72 | AG72: =AF72*_zk03a3*X72 | AH72: =IF(B72,Y72-R72,0) | AI72: =MAX(0,-AH71) | AJ72: =MIN(AI71,MAX(0,(AM71+AL71+AK71+AJ71+AI71)-AN71)) | AK72: =MIN(AJ71,MAX(0,(AM71+AL71+AK71+AJ71)-AN71)) | AL72: =MIN(AK71,MAX(0,(AM71+AL71+AK71)-AN71)) | AM72: =MIN(AL71,MAX(0,(AM71+AL71)-AN71)) | AN72: =MIN(MAX(AH72,0),AI72+AJ72+AK72+AL72+AM72) | AO72: =MAX(AH72,0)-AN72 | AP72: =AO72*_zk03a3*X72 | AQ72: =IF(A72=_zx5hja,_zk1wd3,0) | AR72: =IF(B72,E72-_zkfhzg-M72-O72-F72+AQ72,0) | AS72: =AR72-AG72 | AT72: =IF(B72,E72-_zkfhzg-M72-O72-F72-S72-AP72+AQ72-IF(AND(A72=_zx5hja,_z2al7i>_zx5hja),U72,0),0) | AU72: =AU71+AS72 | AV72: =IF(AND(AU71<0,AU72>=0,AS72>0),1,0) | AW72: =AS72/(1+_z1ltt4)^A72 | AX72: =AX71+AW72 | AY72: =IF(AND(AX71<0,AX72>=0,AW72>0),1,0) | AZ72: =(_z39asj+_zy2ig8)*C72 | BA72: =IF(B72,_zkfhzg+_zdd3mz+_z2y4dt+F72-AQ72,0) | BB72: =IF(AR72=0,BB71,SIGN(AR72)) | BC72: =BC71+IF(OR(AR72=0,BB71=0),0,IF(SIGN(AR72)<>BB71,1,0)) | BD72: =IF(AS72=0,BD71,SIGN(AS72)) | BE72: =BE71+IF(OR(AS72=0,BD71=0),0,IF(SIGN(AS72)<>BD71,1,0)) | BF72: =IF(AT72=0,BF71,SIGN(AT72)) | BG72: =BG71+IF(OR(AT72=0,BF71=0),0,IF(SIGN(AT72)<>BF71,1,0))
A73: 9 | B73: =AND(A73>=1,A73<=_zx5hja) | C73: =IF(B73,(1-_zecdlb)^(A73-1),0) | D73: =(_zgk3lw+_z7m6d8)*C73 | E73: =IF(B73,D73+_zmztd5-_zdd3mz-_z2y4dt,0) | F73: =IF(AND(B73,A73=_ztfkfy),_z4p8is*_zh30bl,0) | G73: =F73*0.13/(1+0.13) | H73: =F73-G73 | I73: =IF(B73,_z7m6d8*C73+_zz1w2z,0) | J73: =I73/(1+0.13) | K73: =I73-J73 | L73: =N72+G73 | M73: =MAX(0,K73-L73) | N73: =MAX(0,L73-K73) | O73: =M73*0.12 | P73: =E73-K73 | Q73: =U72 | R73: =IF(AND(B73,A73<=_z2al7i),Q73*_zks9j8,0) | S73: =IF(AND(B73,A73<=_z2al7i),_zgsfrl,0) | T73: =S73-R73 | U73: =MAX(0,Q73-T73) | V73: =IF(AND(B73,A73<=_zupe8l),_z0jo6h,0) | W73: =IF((_zlt415="是"),IF(A73<=3,0,IF(A73<=6,0.5,1)),1) | X73: =_zrzkf6*W73+(1-_zrzkf6) | Y73: =IF(B73,P73-_zkfhzg-O73-V73-H73,0) | Z73: =MAX(0,-Y72) | AA73: =MIN(Z72,MAX(0,(AD72+AC72+AB72+AA72+Z72)-AE72)) | AB73: =MIN(AA72,MAX(0,(AD72+AC72+AB72+AA72)-AE72)) | AC73: =MIN(AB72,MAX(0,(AD72+AC72+AB72)-AE72)) | AD73: =MIN(AC72,MAX(0,(AD72+AC72)-AE72)) | AE73: =MIN(MAX(Y73,0),Z73+AA73+AB73+AC73+AD73) | AF73: =MAX(Y73,0)-AE73 | AG73: =AF73*_zk03a3*X73 | AH73: =IF(B73,Y73-R73,0) | AI73: =MAX(0,-AH72) | AJ73: =MIN(AI72,MAX(0,(AM72+AL72+AK72+AJ72+AI72)-AN72)) | AK73: =MIN(AJ72,MAX(0,(AM72+AL72+AK72+AJ72)-AN72)) | AL73: =MIN(AK72,MAX(0,(AM72+AL72+AK72)-AN72)) | AM73: =MIN(AL72,MAX(0,(AM72+AL72)-AN72)) | AN73: =MIN(MAX(AH73,0),AI73+AJ73+AK73+AL73+AM73) | AO73: =MAX(AH73,0)-AN73 | AP73: =AO73*_zk03a3*X73 | AQ73: =IF(A73=_zx5hja,_zk1wd3,0) | AR73: =IF(B73,E73-_zkfhzg-M73-O73-F73+AQ73,0) | AS73: =AR73-AG73 | AT73: =IF(B73,E73-_zkfhzg-M73-O73-F73-S73-AP73+AQ73-IF(AND(A73=_zx5hja,_z2al7i>_zx5hja),U73,0),0) | AU73: =AU72+AS73 | AV73: =IF(AND(AU72<0,AU73>=0,AS73>0),1,0) | AW73: =AS73/(1+_z1ltt4)^A73 | AX73: =AX72+AW73 | AY73: =IF(AND(AX72<0,AX73>=0,AW73>0),1,0) | AZ73: =(_z39asj+_zy2ig8)*C73 | BA73: =IF(B73,_zkfhzg+_zdd3mz+_z2y4dt+F73-AQ73,0) | BB73: =IF(AR73=0,BB72,SIGN(AR73)) | BC73: =BC72+IF(OR(AR73=0,BB72=0),0,IF(SIGN(AR73)<>BB72,1,0)) | BD73: =IF(AS73=0,BD72,SIGN(AS73)) | BE73: =BE72+IF(OR(AS73=0,BD72=0),0,IF(SIGN(AS73)<>BD72,1,0)) | BF73: =IF(AT73=0,BF72,SIGN(AT73)) | BG73: =BG72+IF(OR(AT73=0,BF72=0),0,IF(SIGN(AT73)<>BF72,1,0))
A74: 10 | B74: =AND(A74>=1,A74<=_zx5hja) | C74: =IF(B74,(1-_zecdlb)^(A74-1),0) | D74: =(_zgk3lw+_z7m6d8)*C74 | E74: =IF(B74,D74+_zmztd5-_zdd3mz-_z2y4dt,0) | F74: =IF(AND(B74,A74=_ztfkfy),_z4p8is*_zh30bl,0) | G74: =F74*0.13/(1+0.13) | H74: =F74-G74 | I74: =IF(B74,_z7m6d8*C74+_zz1w2z,0) | J74: =I74/(1+0.13) | K74: =I74-J74 | L74: =N73+G74 | M74: =MAX(0,K74-L74) | N74: =MAX(0,L74-K74) | O74: =M74*0.12 | P74: =E74-K74 | Q74: =U73 | R74: =IF(AND(B74,A74<=_z2al7i),Q74*_zks9j8,0) | S74: =IF(AND(B74,A74<=_z2al7i),_zgsfrl,0) | T74: =S74-R74 | U74: =MAX(0,Q74-T74) | V74: =IF(AND(B74,A74<=_zupe8l),_z0jo6h,0) | W74: =IF((_zlt415="是"),IF(A74<=3,0,IF(A74<=6,0.5,1)),1) | X74: =_zrzkf6*W74+(1-_zrzkf6) | Y74: =IF(B74,P74-_zkfhzg-O74-V74-H74,0) | Z74: =MAX(0,-Y73) | AA74: =MIN(Z73,MAX(0,(AD73+AC73+AB73+AA73+Z73)-AE73)) | AB74: =MIN(AA73,MAX(0,(AD73+AC73+AB73+AA73)-AE73)) | AC74: =MIN(AB73,MAX(0,(AD73+AC73+AB73)-AE73)) | AD74: =MIN(AC73,MAX(0,(AD73+AC73)-AE73)) | AE74: =MIN(MAX(Y74,0),Z74+AA74+AB74+AC74+AD74) | AF74: =MAX(Y74,0)-AE74 | AG74: =AF74*_zk03a3*X74 | AH74: =IF(B74,Y74-R74,0) | AI74: =MAX(0,-AH73) | AJ74: =MIN(AI73,MAX(0,(AM73+AL73+AK73+AJ73+AI73)-AN73)) | AK74: =MIN(AJ73,MAX(0,(AM73+AL73+AK73+AJ73)-AN73)) | AL74: =MIN(AK73,MAX(0,(AM73+AL73+AK73)-AN73)) | AM74: =MIN(AL73,MAX(0,(AM73+AL73)-AN73)) | AN74: =MIN(MAX(AH74,0),AI74+AJ74+AK74+AL74+AM74) | AO74: =MAX(AH74,0)-AN74 | AP74: =AO74*_zk03a3*X74 | AQ74: =IF(A74=_zx5hja,_zk1wd3,0) | AR74: =IF(B74,E74-_zkfhzg-M74-O74-F74+AQ74,0) | AS74: =AR74-AG74 | AT74: =IF(B74,E74-_zkfhzg-M74-O74-F74-S74-AP74+AQ74-IF(AND(A74=_zx5hja,_z2al7i>_zx5hja),U74,0),0) | AU74: =AU73+AS74 | AV74: =IF(AND(AU73<0,AU74>=0,AS74>0),1,0) | AW74: =AS74/(1+_z1ltt4)^A74 | AX74: =AX73+AW74 | AY74: =IF(AND(AX73<0,AX74>=0,AW74>0),1,0) | AZ74: =(_z39asj+_zy2ig8)*C74 | BA74: =IF(B74,_zkfhzg+_zdd3mz+_z2y4dt+F74-AQ74,0) | BB74: =IF(AR74=0,BB73,SIGN(AR74)) | BC74: =BC73+IF(OR(AR74=0,BB73=0),0,IF(SIGN(AR74)<>BB73,1,0)) | BD74: =IF(AS74=0,BD73,SIGN(AS74)) | BE74: =BE73+IF(OR(AS74=0,BD73=0),0,IF(SIGN(AS74)<>BD73,1,0)) | BF74: =IF(AT74=0,BF73,SIGN(AT74)) | BG74: =BG73+IF(OR(AT74=0,BF73=0),0,IF(SIGN(AT74)<>BF73,1,0))
A75: 11 | B75: =AND(A75>=1,A75<=_zx5hja) | C75: =IF(B75,(1-_zecdlb)^(A75-1),0) | D75: =(_zgk3lw+_z7m6d8)*C75 | E75: =IF(B75,D75+_zmztd5-_zdd3mz-_z2y4dt,0) | F75: =IF(AND(B75,A75=_ztfkfy),_z4p8is*_zh30bl,0) | G75: =F75*0.13/(1+0.13) | H75: =F75-G75 | I75: =IF(B75,_z7m6d8*C75+_zz1w2z,0) | J75: =I75/(1+0.13) | K75: =I75-J75 | L75: =N74+G75 | M75: =MAX(0,K75-L75) | N75: =MAX(0,L75-K75) | O75: =M75*0.12 | P75: =E75-K75 | Q75: =U74 | R75: =IF(AND(B75,A75<=_z2al7i),Q75*_zks9j8,0) | S75: =IF(AND(B75,A75<=_z2al7i),_zgsfrl,0) | T75: =S75-R75 | U75: =MAX(0,Q75-T75) | V75: =IF(AND(B75,A75<=_zupe8l),_z0jo6h,0) | W75: =IF((_zlt415="是"),IF(A75<=3,0,IF(A75<=6,0.5,1)),1) | X75: =_zrzkf6*W75+(1-_zrzkf6) | Y75: =IF(B75,P75-_zkfhzg-O75-V75-H75,0) | Z75: =MAX(0,-Y74) | AA75: =MIN(Z74,MAX(0,(AD74+AC74+AB74+AA74+Z74)-AE74)) | AB75: =MIN(AA74,MAX(0,(AD74+AC74+AB74+AA74)-AE74)) | AC75: =MIN(AB74,MAX(0,(AD74+AC74+AB74)-AE74)) | AD75: =MIN(AC74,MAX(0,(AD74+AC74)-AE74)) | AE75: =MIN(MAX(Y75,0),Z75+AA75+AB75+AC75+AD75) | AF75: =MAX(Y75,0)-AE75 | AG75: =AF75*_zk03a3*X75 | AH75: =IF(B75,Y75-R75,0) | AI75: =MAX(0,-AH74) | AJ75: =MIN(AI74,MAX(0,(AM74+AL74+AK74+AJ74+AI74)-AN74)) | AK75: =MIN(AJ74,MAX(0,(AM74+AL74+AK74+AJ74)-AN74)) | AL75: =MIN(AK74,MAX(0,(AM74+AL74+AK74)-AN74)) | AM75: =MIN(AL74,MAX(0,(AM74+AL74)-AN74)) | AN75: =MIN(MAX(AH75,0),AI75+AJ75+AK75+AL75+AM75) | AO75: =MAX(AH75,0)-AN75 | AP75: =AO75*_zk03a3*X75 | AQ75: =IF(A75=_zx5hja,_zk1wd3,0) | AR75: =IF(B75,E75-_zkfhzg-M75-O75-F75+AQ75,0) | AS75: =AR75-AG75 | AT75: =IF(B75,E75-_zkfhzg-M75-O75-F75-S75-AP75+AQ75-IF(AND(A75=_zx5hja,_z2al7i>_zx5hja),U75,0),0) | AU75: =AU74+AS75 | AV75: =IF(AND(AU74<0,AU75>=0,AS75>0),1,0) | AW75: =AS75/(1+_z1ltt4)^A75 | AX75: =AX74+AW75 | AY75: =IF(AND(AX74<0,AX75>=0,AW75>0),1,0) | AZ75: =(_z39asj+_zy2ig8)*C75 | BA75: =IF(B75,_zkfhzg+_zdd3mz+_z2y4dt+F75-AQ75,0) | BB75: =IF(AR75=0,BB74,SIGN(AR75)) | BC75: =BC74+IF(OR(AR75=0,BB74=0),0,IF(SIGN(AR75)<>BB74,1,0)) | BD75: =IF(AS75=0,BD74,SIGN(AS75)) | BE75: =BE74+IF(OR(AS75=0,BD74=0),0,IF(SIGN(AS75)<>BD74,1,0)) | BF75: =IF(AT75=0,BF74,SIGN(AT75)) | BG75: =BG74+IF(OR(AT75=0,BF74=0),0,IF(SIGN(AT75)<>BF74,1,0))
A76: 12 | B76: =AND(A76>=1,A76<=_zx5hja) | C76: =IF(B76,(1-_zecdlb)^(A76-1),0) | D76: =(_zgk3lw+_z7m6d8)*C76 | E76: =IF(B76,D76+_zmztd5-_zdd3mz-_z2y4dt,0) | F76: =IF(AND(B76,A76=_ztfkfy),_z4p8is*_zh30bl,0) | G76: =F76*0.13/(1+0.13) | H76: =F76-G76 | I76: =IF(B76,_z7m6d8*C76+_zz1w2z,0) | J76: =I76/(1+0.13) | K76: =I76-J76 | L76: =N75+G76 | M76: =MAX(0,K76-L76) | N76: =MAX(0,L76-K76) | O76: =M76*0.12 | P76: =E76-K76 | Q76: =U75 | R76: =IF(AND(B76,A76<=_z2al7i),Q76*_zks9j8,0) | S76: =IF(AND(B76,A76<=_z2al7i),_zgsfrl,0) | T76: =S76-R76 | U76: =MAX(0,Q76-T76) | V76: =IF(AND(B76,A76<=_zupe8l),_z0jo6h,0) | W76: =IF((_zlt415="是"),IF(A76<=3,0,IF(A76<=6,0.5,1)),1) | X76: =_zrzkf6*W76+(1-_zrzkf6) | Y76: =IF(B76,P76-_zkfhzg-O76-V76-H76,0) | Z76: =MAX(0,-Y75) | AA76: =MIN(Z75,MAX(0,(AD75+AC75+AB75+AA75+Z75)-AE75)) | AB76: =MIN(AA75,MAX(0,(AD75+AC75+AB75+AA75)-AE75)) | AC76: =MIN(AB75,MAX(0,(AD75+AC75+AB75)-AE75)) | AD76: =MIN(AC75,MAX(0,(AD75+AC75)-AE75)) | AE76: =MIN(MAX(Y76,0),Z76+AA76+AB76+AC76+AD76) | AF76: =MAX(Y76,0)-AE76 | AG76: =AF76*_zk03a3*X76 | AH76: =IF(B76,Y76-R76,0) | AI76: =MAX(0,-AH75) | AJ76: =MIN(AI75,MAX(0,(AM75+AL75+AK75+AJ75+AI75)-AN75)) | AK76: =MIN(AJ75,MAX(0,(AM75+AL75+AK75+AJ75)-AN75)) | AL76: =MIN(AK75,MAX(0,(AM75+AL75+AK75)-AN75)) | AM76: =MIN(AL75,MAX(0,(AM75+AL75)-AN75)) | AN76: =MIN(MAX(AH76,0),AI76+AJ76+AK76+AL76+AM76) | AO76: =MAX(AH76,0)-AN76 | AP76: =AO76*_zk03a3*X76 | AQ76: =IF(A76=_zx5hja,_zk1wd3,0) | AR76: =IF(B76,E76-_zkfhzg-M76-O76-F76+AQ76,0) | AS76: =AR76-AG76 | AT76: =IF(B76,E76-_zkfhzg-M76-O76-F76-S76-AP76+AQ76-IF(AND(A76=_zx5hja,_z2al7i>_zx5hja),U76,0),0) | AU76: =AU75+AS76 | AV76: =IF(AND(AU75<0,AU76>=0,AS76>0),1,0) | AW76: =AS76/(1+_z1ltt4)^A76 | AX76: =AX75+AW76 | AY76: =IF(AND(AX75<0,AX76>=0,AW76>0),1,0) | AZ76: =(_z39asj+_zy2ig8)*C76 | BA76: =IF(B76,_zkfhzg+_zdd3mz+_z2y4dt+F76-AQ76,0) | BB76: =IF(AR76=0,BB75,SIGN(AR76)) | BC76: =BC75+IF(OR(AR76=0,BB75=0),0,IF(SIGN(AR76)<>BB75,1,0)) | BD76: =IF(AS76=0,BD75,SIGN(AS76)) | BE76: =BE75+IF(OR(AS76=0,BD75=0),0,IF(SIGN(AS76)<>BD75,1,0)) | BF76: =IF(AT76=0,BF75,SIGN(AT76)) | BG76: =BG75+IF(OR(AT76=0,BF75=0),0,IF(SIGN(AT76)<>BF75,1,0))
... A89: 25 | B89: =AND(A89>=1,A89<=_zx5hja) | C89: =IF(B89,(1-_zecdlb)^(A89-1),0) | D89: =(_zgk3lw+_z7m6d8)*C89 | E89: =IF(B89,D89+_zmztd5-_zdd3mz-_z2y4dt,0) | F89: =IF(AND(B89,A89=_ztfkfy),_z4p8is*_zh30bl,0) | G89: =F89*0.13/(1+0.13) | H89: =F89-G89 | I89: =IF(B89,_z7m6d8*C89+_zz1w2z,0) | J89: =I89/(1+0.13) | K89: =I89-J89 | L89: =N88+G89 | M89: =MAX(0,K89-L89) | N89: =MAX(0,L89-K89) | O89: =M89*0.12 | P89: =E89-K89 | Q89: =U88 | R89: =IF(AND(B89,A89<=_z2al7i),Q89*_zks9j8,0) | S89: =IF(AND(B89,A89<=_z2al7i),_zgsfrl,0) | T89: =S89-R89 | U89: =MAX(0,Q89-T89) | V89: =IF(AND(B89,A89<=_zupe8l),_z0jo6h,0) | W89: =IF((_zlt415="是"),IF(A89<=3,0,IF(A89<=6,0.5,1)),1) | X89: =_zrzkf6*W89+(1-_zrzkf6) | Y89: =IF(B89,P89-_zkfhzg-O89-V89-H89,0) | Z89: =MAX(0,-Y88) | AA89: =MIN(Z88,MAX(0,(AD88+AC88+AB88+AA88+Z88)-AE88)) | AB89: =MIN(AA88,MAX(0,(AD88+AC88+AB88+AA88)-AE88)) | AC89: =MIN(AB88,MAX(0,(AD88+AC88+AB88)-AE88)) | AD89: =MIN(AC88,MAX(0,(AD88+AC88)-AE88)) | AE89: =MIN(MAX(Y89,0),Z89+AA89+AB89+AC89+AD89) | AF89: =MAX(Y89,0)-AE89 | AG89: =AF89*_zk03a3*X89 | AH89: =IF(B89,Y89-R89,0) | AI89: =MAX(0,-AH88) | AJ89: =MIN(AI88,MAX(0,(AM88+AL88+AK88+AJ88+AI88)-AN88)) | AK89: =MIN(AJ88,MAX(0,(AM88+AL88+AK88+AJ88)-AN88)) | AL89: =MIN(AK88,MAX(0,(AM88+AL88+AK88)-AN88)) | AM89: =MIN(AL88,MAX(0,(AM88+AL88)-AN88)) | AN89: =MIN(MAX(AH89,0),AI89+AJ89+AK89+AL89+AM89) | AO89: =MAX(AH89,0)-AN89 | AP89: =AO89*_zk03a3*X89 | AQ89: =IF(A89=_zx5hja,_zk1wd3,0) | AR89: =IF(B89,E89-_zkfhzg-M89-O89-F89+AQ89,0) | AS89: =AR89-AG89 | AT89: =IF(B89,E89-_zkfhzg-M89-O89-F89-S89-AP89+AQ89-IF(AND(A89=_zx5hja,_z2al7i>_zx5hja),U89,0),0) | AU89: =AU88+AS89 | AV89: =IF(AND(AU88<0,AU89>=0,AS89>0),1,0) | AW89: =AS89/(1+_z1ltt4)^A89 | AX89: =AX88+AW89 | AY89: =IF(AND(AX88<0,AX89>=0,AW89>0),1,0) | AZ89: =(_z39asj+_zy2ig8)*C89 | BA89: =IF(B89,_zkfhzg+_zdd3mz+_z2y4dt+F89-AQ89,0) | BB89: =IF(AR89=0,BB88,SIGN(AR89)) | BC89: =BC88+IF(OR(AR89=0,BB88=0),0,IF(SIGN(AR89)<>BB88,1,0)) | BD89: =IF(AS89=0,BD88,SIGN(AS89)) | BE89: =BE88+IF(OR(AS89=0,BD88=0),0,IF(SIGN(AS89)<>BD88,1,0)) | BF89: =IF(AT89=0,BF88,SIGN(AT89)) | BG89: =BG88+IF(OR(AT89=0,BF88=0),0,IF(SIGN(AT89)<>BF88,1,0))
A91: chk_pre_lo | B91: =SUMPRODUCT(_z9arcc,0.01^-_zc53rh)
A92: chk_pre_hi | B92: =SUMPRODUCT(_z9arcc,4^-_zc53rh)
A93: chk_post_lo | B93: =SUMPRODUCT(_ze1s6n,0.01^-_zc53rh)
A94: chk_post_hi | B94: =SUMPRODUCT(_ze1s6n,4^-_zc53rh)
A95: chk_eq_lo | B95: =SUMPRODUCT(_zfbj01,0.01^-_zc53rh)
A96: chk_eq_hi | B96: =SUMPRODUCT(_zfbj01,4^-_zc53rh)
A97: irr_pre | B97: =IF(_z9rhi7>25,"运营期超25年·请用网页版测算",IF(_zsqbm8*_zzj3wj>0,IF(BC89>1,"非常规现金流，须人工复核","全周期未回收"),IFERROR(IRR(_z9arcc),"—")))
A98: irr_post | B98: =IF(_z9rhi7>25,"运营期超25年·请用网页版测算",IF(_zqsho0*_zpy13v>0,IF(BE89>1,"非常规现金流，须人工复核","全周期未回收"),IFERROR(IRR(_ze1s6n),"—")))
A99: irr_eq | B99: =IF(_z9rhi7>25,"运营期超25年·请用网页版测算",IF(_zxdbxd*_ztsxiq>0,IF(BG89>1,"非常规现金流，须人工复核","全周期未回收"),IFERROR(IRR(_zfbj01),"—")))
A100: npv | B100: =IF(_z9rhi7>25,"运营期超25年·请用网页版测算",INDEX(_ze1s6n,1)+NPV(_z1ltt4,_zlo46y))
A101: payback_s | B101: =IF(_z9rhi7>25,"运营期超25年·请用网页版测算",IFERROR(MATCH(1,_z4ca63,0)-2+ABS(INDEX(_zeuabd,MATCH(1,_z4ca63,0)-1))/INDEX(_ze1s6n,MATCH(1,_z4ca63,0)),"超运营期"))
A102: payback_d | B102: =IF(_z9rhi7>25,"运营期超25年·请用网页版测算",IFERROR(MATCH(1,_zo2cnc,0)-2+ABS(INDEX(_zxzots,MATCH(1,_zo2cnc,0)-1))/INDEX(_zxlxm4,MATCH(1,_zo2cnc,0)),"超运营期"))
A103: lcoe | B103: =IF(_z9rhi7>25,"运营期超25年·请用网页版测算",IF(NPV(_z1ltt4,_zgl7j8)>0,(_zbb0h1+NPV(_z1ltt4,_zzgx74))/NPV(_z1ltt4,_zgl7j8),"—"))
