Workbook
Name _zqgx7v: '_参数'!$H$3:$H$36
Name _zk618t: '_参数'!$A$3:$A$132
Name _zixjw6: '_参数'!$D$3:$D$132
Name _zwjvbx: '_参数'!$E$3:$E$132
Name _zf8jb3: '_参数'!$F$3:$F$132
Name _zkrpcw: '测算'!$C$5
Name _zlj03i: '测算'!$C$6
Name _z3xkci: '测算'!$C$7
Name _zcshgi: '测算'!$C$8
Name _zhsdpd: '测算'!$C$9
Name _zghnzo: '测算'!$C$12
Name _z82y2b: '测算'!$C$13
Name _zp8xhg: '测算'!$C$14
Name _zx32ce: '测算'!$C$15
Name _zksy9m: '测算'!$C$16
Name _z35wsg: '测算'!$C$20
Name _zix1lp: '测算'!$C$21
Name _z4kl0k: '测算'!$C$22
Name _z98gva: '测算'!$C$23
Name _zrb6fn: '测算'!$C$24
Name _zjttpb: '测算'!$C$25
Name _zbhssj: '测算'!$C$26
Name _zzoaus: '测算'!$C$27
Name _zftf5w: '测算'!$C$30
Name _z6mxd8: '测算'!$C$31
Name _zvtsqd: '测算'!$C$32
Name _zg5443: '测算'!$C$33
Name _zk8d4f: '测算'!$C$36
Name _zhw65s: '测算'!$C$37
Name _zf2rqb: '测算'!$C$38
Name _zsw7bq: '测算'!$C$39
Name _z3m5k2: '测算'!$C$40
Name _z5ctcx: '测算'!$C$41
Name _zysee0: '测算'!$C$42
Name _z78i0e: '测算'!$C$43
Name _zw04od: '测算'!$C$44
Name _z8d2zq: '测算'!$C$45
Name _zzvbgr: '测算'!$C$48
Name _zzl39o: '测算'!$C$49
Name _zm9z4k: '测算'!$C$50
Name _zbf04s: '测算'!$C$51
Name _z1v75m: '测算'!$C$52
Name _zyywx7: '测算'!$C$53
Name _z0ek84: '测算'!$C$54
Name _z7fj0w: '测算'!$C$55
Name _zia8ld: '测算'!$C$56
Name _z5jv12: '测算'!$C$57
Name _zl8371: '测算'!$C$58
Name _z5sfpo: '测算'!$C$59
Name _z7ukau: '测算'!$C$60
Name _zno06c: '测算'!$C$61
Name _ze4vc7: '测算'!$C$62
Name _zqudm6: '测算'!$C$63
Name _z52v2x: '测算'!$C$64
Name _zs8hxw: '测算'!$C$65
Name _zpnfsf: '测算'!$C$66
Name _zawtbl: '测算'!$C$67
Name _ziqmyk: '测算'!$C$68
Name _z0m7ys: '测算'!$C$69
Name _zstij9: '_引擎'!$B$2

Sheet 说明
B2: 绿电直连经济测算 v4.0 · 介子九维 JIEZIJIUWEI
B3: 版本 v4.0 · 2026年8月1日 · 建设期利息与度电成本更换支出口径更新。
B4: 来源：第四监管周期省级输配电价表（附件1），更新日期2026-07-10。区域电网输电价格表（附件2）仅在网站独立查询，不自动计入本测算公式。
B6: 使用方法
B7: 第一步：在「测算」表输入区修改黄底单元格（下拉项从列表选择），其余区域为自动计算。
B8: 第二步：查看结果区的关键指标、合规判定、构成分析与逐年现金流，全簿公式即时重算。
B9: 第三步：需要留存比对的方案，将本文件另存副本后再改参数，避免覆盖原方案。
B10: Excel 版填写内容不会自动保存，填写后请另存为您自己的副本，即可长期保存并随时接着用；网页版与小程序版已支持本机自动留存填写内容。
B12: 测算口径
B13: 财务评价采用融资前（全投资）与融资后（资本金）双口径现金流；投资按含税全额期初流出，现金流入按含税收入、流出扣实缴增值税，可抵扣进项税通过少缴销项逐年回收；折旧计税基数不含可抵扣进项税，年折旧额分母恒用税法折旧年限，期末回收固定资产余值（残值与未折旧账面净值）；更换性支出当年费用化税前扣除、进项税补入抵扣池；亏损按税法结转以后五个年度弥补，全投资与资本金口径各设独立亏损池；三免三减半优惠按光伏、风电投资占比份额化。
B14: 项目总投资含建设期利息，建设期按1年、当年借款按半年计息；建设期利息进入资本金口径资产基础，不进入全投资口径。土地取得费不计提建设期利息，多年建设期暂不支持。
B15: 储能更换支出计入度电成本时按不含可抵扣进项税额的净额，现金流出仍按含税全额。
... B26: 预设参数可直接使用，也可按项目实际逐项修改；正式测算前请结合项目实际核实取值。各参数的含义与填报要点见输入区单元格批注。

Sheet 总览
B1: 绿电直连经济测算 · 总览 | P1: 介子九维 JIEZIJIUWEI
B2: ="当前参数下：税后全投资内部收益率 "&TEXT(_z3ewnh,"0.00%")&"，静态回收期 "&TEXT(_z3lcbu,"0.0")&" 年，年节省 "&TEXT(_zmorcm,"#,##0")&" 万元"
B4: 全投资内部收益率（税后） | F4: 净现值（税后全投资） | J4: 项目总投资（含建设期利息） | N4: 静态回收期 | R4: 度电成本 LCOE
B5: =_z3ewnh | F5: =_z8sr6o | J5: =_z32w4e | N5: =_z3lcbu | R5: =_zehl1m
B6: 主评价指标 | F6: 万元 | J6: 万元 | N6: 年 | R6: 元/kWh
B41: 结果随「测算」表输入即时更新；测算口径与边界声明见「说明」。 | P41: 介子九维 JIEZIJIUWEI

Sheet _参数
A1: 省级电网输配电价矩阵（第四监管周期，附件1）
A2: 键 | B2: 价区 | C2: 电压等级 | D2: 电度电价 | E2: 需量电价 | F2: 容量电价
A3: 北京|1~10(20)千伏 | B3: 北京 | C3: 1~10(20)千伏 | D3: 0.205 | E3: 52 | F3: 33 | H3: 北京
A4: 北京|35千伏 | B4: 北京 | C4: 35千伏 | D4: 0.165 | E4: 48 | F4: 30 | H4: 天津
A5: 北京|110千伏 | B5: 北京 | C5: 110千伏 | D5: 0.165 | E5: 48 | F5: 30 | H5: 河北（南网价区）
A6: 北京|220千伏及以上 | B6: 北京 | C6: 220千伏及以上 | D6: 0.15 | E6: 45 | F6: 28 | H6: 冀北
A7: 天津|1~10(20)千伏 | B7: 天津 | C7: 1~10(20)千伏 | D7: 0.1631 | E7: 43.2 | F7: 27 | H7: 山西
A8: 天津|35千伏 | B8: 天津 | C8: 35千伏 | D8: 0.1402 | E8: 40 | F8: 25 | H8: 蒙东
A9: 天津|110千伏 | B9: 天津 | C9: 110千伏 | D9: 0.1264 | E9: 40 | F9: 25 | H9: 蒙西（内蒙古电力）
A10: 天津|220千伏及以上 | B10: 天津 | C10: 220千伏及以上 | D10: 0.1052 | E10: 36.8 | F10: 23 | H10: 辽宁
A11: 河北（南网价区）|1~10(20)千伏 | B11: 河北（南网价区） | C11: 1~10(20)千伏 | D11: 0.1476 | E11: 35.2 | F11: 22 | H11: 吉林
A12: 河北（南网价区）|35千伏 | B12: 河北（南网价区） | C12: 35千伏 | D12: 0.1226 | E12: 33.6 | F12: 21 | H12: 黑龙江
A13: 河北（南网价区）|110千伏 | B13: 河北（南网价区） | C13: 110千伏 | D13: 0.0976 | E13: 32 | F13: 20 | H13: 上海
A14: 河北（南网价区）|220千伏及以上 | B14: 河北（南网价区） | C14: 220千伏及以上 | D14: 0.0726 | E14: 30.4 | F14: 19 | H14: 江苏
... A36: 吉林|220千伏及以上 | B36: 吉林 | C36: 220千伏及以上 | D36: 0.1113 | E36: 36.8 | F36: 23 | H36: 新疆
A37: 黑龙江|1~10(20)千伏 | B37: 黑龙江 | C37: 1~10(20)千伏 | D37: 0.1385 | E37: 36.8 | F37: 23
A38: 黑龙江|35千伏 | B38: 黑龙江 | C38: 35千伏 | D38: 0.1171 | E38: 36.8 | F38: 23
A39: 黑龙江|110千伏 | B39: 黑龙江 | C39: 110千伏 | D39: 0.1026 | E39: 35.2 | F39: 22
A40: 黑龙江|220千伏及以上 | B40: 黑龙江 | C40: 220千伏及以上 | D40: 0.0763 | E40: 35.2 | F40: 22
A41: 上海|1~10(20)千伏 | B41: 上海 | C41: 1~10(20)千伏 | D41: 0.1623 | E41: 44.8 | F41: 28
A42: 上海|35千伏 | B42: 上海 | C42: 35千伏 | D42: 0.1268 | E42: 41.6 | F42: 26
A43: 上海|110千伏 | B43: 上海 | C43: 110千伏 | D43: 0.0953 | E43: 38.4 | F43: 24
A44: 上海|220千伏及以上 | B44: 上海 | C44: 220千伏及以上 | D44: 0.0851 | E44: 35.2 | F44: 22
A45: 江苏|1~10(20)千伏 | B45: 江苏 | C45: 1~10(20)千伏 | D45: 0.1298 | E45: 51.2 | F45: 32
A46: 江苏|35千伏 | B46: 江苏 | C46: 35千伏 | D46: 0.1048 | E46: 48 | F46: 30
A47: 江苏|110千伏 | B47: 江苏 | C47: 110千伏 | D47: 0.0788 | E47: 44.8 | F47: 28
A48: 江苏|220千伏及以上 | B48: 江苏 | C48: 220千伏及以上 | D48: 0.0518 | E48: 41.6 | F48: 26
... A132: 新疆|220千伏及以上 | B132: 新疆 | C132: 220千伏及以上 | D132: 0.0485 | E132: 30.4 | F132: 19

Sheet 测算
B1: 绿电直连经济测算 v4.0 · 介子九维 JIEZIJIUWEI
B2: 输入区（黄底蓝字可修改；带出值为预设，填「覆盖值」栏替代；批注含填报说明）
B3: 参数 | C3: 数值 | D3: 单位 | E3: 覆盖值 | H3: 关键指标
B4: 模式开关 | H4: 全投资内部收益率（税前） | I4: =_zvfwiv
B5: 项目形态 | C5: 并网型 | H5: 全投资内部收益率（税后） | I5: =_z3ewnh | J5: 主评价指标
B6: 输配电费方式 | C6: 单一容量制 | H6: 资本金内部收益率 | I6: =_z2tbwe
B7: 现行容（需）量电费计费方式 | C7: 按容量 | H7: 净现值（税后全投资） | I7: =_z8sr6o | J7: 万元
B8: 基金计费口径 | C8: 下网+自用 | H8: 静态回收期 | I8: =_z3lcbu | J8: 年
B9: 所得税三免三减半 | C9: 否 | H9: 动态回收期 | I9: =_z4kqsx | J9: 年
H10: 度电成本 LCOE | I10: =_zehl1m | J10: 元/kWh
B11: 价区与输配电价 | H11: 综合到户电价 | I11: =_z3179u | J11: 元/kWh
B12: 价区 | C12: 山东 | H12: 年节省额（对照电网购电） | I12: =_zmorcm | J12: 万元
B13: 接入电压等级 | C13: 110千伏 | H13: 节省率 | I13: =_zhg1yd
B14: 输配电度电价 | C14: =IF(ISNUMBER($E$14),$E$14,IFERROR(INDEX(_zixjw6,MATCH(_zghnzo&"|"&_z82y2b,_zk618t,0)),0)) | D14: 元/kWh | H14: 绿证/CBAM规避价值（单列） | I14: =_zc82pq | J14: 万元
B15: 需量电价 | C15: =IF(ISNUMBER($E$15),$E$15,IFERROR(INDEX(_zwjvbx,MATCH(_zghnzo&"|"&_z82y2b,_zk618t,0)),0)) | D15: 元/kW·月
B16: 容量电价 | C16: =IF(ISNUMBER($E$16),$E$16,IFERROR(INDEX(_zf8jb3,MATCH(_zghnzo&"|"&_z82y2b,_zk618t,0)),0)) | D16: 元/kVA·月 | H16: 合规判定（绿电直连准入红线）
B17: =IF(ISNA(MATCH(_zghnzo&"|"&_z82y2b,_zk618t,0)),"所选价区无此电压档，请改选电压等级或填写覆盖值","") | H17: 自发自用/可用发电量 ≥60% | I17: =_zkt2jm | J17: =IF(_zkt2jm>=0.6,"通过","不满足")
H18: 自发自用/年用电量 ≥30% | I18: =_zy8wik | J18: =IF(_zy8wik>=0.3,"通过","不满足")
B19: A 项目基础 | H19: 上网电量/可用发电量 ≤20% | I19: =_zl0ecr | J19: =IF((_zkrpcw="离网型"),"通过（离网不适用）",IF(_zl0ecr<=0.2,"通过","不满足"))
B20: 光伏装机 | C20: 100 | D20: MW
B21: 光伏年利用小时 | C21: 1100 | D21: h | H21: 投资与费用构成
B22: 风电装机 | C22: 0 | D22: MW | H22: 光伏投资 | I22: =_zkh06o | J22: 万元
B23: 风电年利用小时 | C23: 0 | D23: h | H23: 风电投资 | I23: =_z517d3 | J23: 万元
B24: 储能功率 | C24: 20 | D24: MW | H24: 储能投资 | I24: =_z67r2o | J24: 万元
B25: 储能容量 | C25: 40 | D25: MWh | H25: 专线及升压投资 | I25: =_zbf04s | J25: 万元
B26: 接入公网容量（自主申报） | C26: 25000 | D26: kVA | H26: 土地取得费 | I26: =_z5sfpo | J26: 万元
B27: 申报（合同）最大需量 | C27: 20000 | D27: kW | H27: 建设投资（不含建设期利息） | I27: =_z1tt59 | J27: 万元
H28: 建设期利息 | I28: =_zhc22k | J28: 万元
B29: B 电量 | H29: 项目总投资（含建设期利息） | I29: =_z32w4e | J29: 万元
B30: 用户年用电量 | C30: 12000 | D30: 万kWh | H30: 资本金 | I30: =_zn0hoh | J30: 万元
B31: 年自发自用电量 | C31: 9000 | D31: 万kWh | H31: 贷款 | I31: =_zmqr32 | J31: 万元
B32: 弃电率 | C32: 0.02 | D32: % | H32: 现行容量电费 | I32: =_zektcz | J32: 万元
B33: 年出力衰减率 | C33: 0.005 | D33: % | H33: 输配电量折算费 | I33: =_zdmffp | J33: 万元
H34: 年系统运行费 | I34: =_zqnyts | J34: 万元
B35: C 电价与费用 | H35: 年上网环节线损费 | I35: =_z9r4dl | J35: 万元
B36: 直供电价（协商） | C36: 0.35 | D36: 元/kWh | H36: 年交叉补贴 | I36: =_ze6p1m | J36: 万元
B37: 下网市场购电价 | C37: 0.55 | D37: 元/kWh | H37: 年政府性基金及附加 | I37: =_zpzqxb | J37: 万元
B38: 电网购电对比到户价 | C38: 0.62 | D38: 元/kWh | H38: 年直供电费 | I38: =_zqhyli | J38: 万元
B39: 上网结算均价 | C39: 0.2 | D39: 元/kWh | H39: 年市场购电费 | I39: =_za7fy7 | J39: 万元
B40: 平均负荷率 | C40: 0.55 | D40: % | H40: 年综合用电成本 | I40: =_zvy62p | J40: 万元
B41: 系统运行费单价 | C41: 0.0209 | D41: 元/kWh | H41: 电网购电对照成本 | I41: =_zfzfsr | J41: 万元
B42: 上网环节线损费用单价 | C42: 0.01 | D42: 元/kWh
B43: 政府性基金及附加单价 | C43: 0.02717 | D43: 元/kWh | H43: 综合到户电价对比（元/kWh）
B44: 交叉补贴单价（已并入系统运行费的省份填0） | C44: 0 | D44: 元/kWh | H44: 绿电直连综合到户电价 | I44: =_z3179u | J44: 元/kWh
B45: 绿证/CBAM折算单价（单列） | C45: 0.005 | D45: 元/kWh | H45: 电网购电对比到户价 | I45: =_zf2rqb | J45: 元/kWh
B47: D 投资与财务
B48: 光伏单位投资 | C48: 3 | D48: 元/W
B49: 风电单位投资 | C49: 4.5 | D49: 元/W
B50: 储能单位投资 | C50: 1 | D50: 元/Wh
B51: 专线及升压投资 | C51: 6000 | D51: 万元
B52: 资本金比例 | C52: 0.3 | D52: %
B53: 贷款利率 | C53: 0.045 | D53: %
B54: 贷款年限 | C54: 15 | D54: 年
B55: 运营期 | C55: 25 | D55: 年
B56: 运维费率 | C56: 0.012 | D56: %
B57: 保险费率 | C57: 0.0025 | D57: %
B58: 土地/场地租金（不含税） | C58: 0 | D58: 万元/年
B59: 土地取得费 | C59: 0 | D59: 万元
... B69: 更换费用比例 | C69: 0.5 | D69: %
B71: =IF(_z7fj0w>25,"运营期超过25年上限：年度现金流表最长25年，当前结果不完整，请修改运营期或用介子九维小程序测算","")
B72: =IF(AND(_z5sfpo>0,_z7ukau<=0),"填有土地取得费时应同时填写土地使用权税前摊销年限，否则该笔投资无法计提税前摊销","")
B73: 建设期按1年、当年借款按半年计息；多年建设期暂不支持。
B76: 逐年现金流（万元）
B77: 年份 | C77: 含税收入 | D77: 运维保险及租金 | E77: 实缴增值税 | F77: 附加税费 | G77: 更换支出 | H77: 期末回收 | I77: 所得税（全投资） | J77: 税后全投资净现金流 | K77: 累计 | L77: 资本金净现金流
B78: 0 | C78: ='_引擎'!F66 | D78: 0 | E78: ='_引擎'!M66 | F78: ='_引擎'!O66 | G78: ='_引擎'!I66 | H78: ='_引擎'!AR66 | I78: ='_引擎'!AH66 | J78: ='_引擎'!AU66 | K78: ='_引擎'!AW66 | L78: ='_引擎'!AV66
B79: 1 | C79: ='_引擎'!F67 | D79: =IF('_引擎'!B67,_zkfhzg,0) | E79: ='_引擎'!M67 | F79: ='_引擎'!O67 | G79: ='_引擎'!I67 | H79: ='_引擎'!AR67 | I79: ='_引擎'!AH67 | J79: ='_引擎'!AU67 | K79: ='_引擎'!AW67 | L79: ='_引擎'!AV67
B80: 2 | C80: ='_引擎'!F68 | D80: =IF('_引擎'!B68,_zkfhzg,0) | E80: ='_引擎'!M68 | F80: ='_引擎'!O68 | G80: ='_引擎'!I68 | H80: ='_引擎'!AR68 | I80: ='_引擎'!AH68 | J80: ='_引擎'!AU68 | K80: ='_引擎'!AW68 | L80: ='_引擎'!AV68
B81: 3 | C81: ='_引擎'!F69 | D81: =IF('_引擎'!B69,_zkfhzg,0) | E81: ='_引擎'!M69 | F81: ='_引擎'!O69 | G81: ='_引擎'!I69 | H81: ='_引擎'!AR69 | I81: ='_引擎'!AH69 | J81: ='_引擎'!AU69 | K81: ='_引擎'!AW69 | L81: ='_引擎'!AV69
B82: 4 | C82: ='_引擎'!F70 | D82: =IF('_引擎'!B70,_zkfhzg,0) | E82: ='_引擎'!M70 | F82: ='_引擎'!O70 | G82: ='_引擎'!I70 | H82: ='_引擎'!AR70 | I82: ='_引擎'!AH70 | J82: ='_引擎'!AU70 | K82: ='_引擎'!AW70 | L82: ='_引擎'!AV70
B83: 5 | C83: ='_引擎'!F71 | D83: =IF('_引擎'!B71,_zkfhzg,0) | E83: ='_引擎'!M71 | F83: ='_引擎'!O71 | G83: ='_引擎'!I71 | H83: ='_引擎'!AR71 | I83: ='_引擎'!AH71 | J83: ='_引擎'!AU71 | K83: ='_引擎'!AW71 | L83: ='_引擎'!AV71
B84: 6 | C84: ='_引擎'!F72 | D84: =IF('_引擎'!B72,_zkfhzg,0) | E84: ='_引擎'!M72 | F84: ='_引擎'!O72 | G84: ='_引擎'!I72 | H84: ='_引擎'!AR72 | I84: ='_引擎'!AH72 | J84: ='_引擎'!AU72 | K84: ='_引擎'!AW72 | L84: ='_引擎'!AV72
B85: 7 | C85: ='_引擎'!F73 | D85: =IF('_引擎'!B73,_zkfhzg,0) | E85: ='_引擎'!M73 | F85: ='_引擎'!O73 | G85: ='_引擎'!I73 | H85: ='_引擎'!AR73 | I85: ='_引擎'!AH73 | J85: ='_引擎'!AU73 | K85: ='_引擎'!AW73 | L85: ='_引擎'!AV73
B86: 8 | C86: ='_引擎'!F74 | D86: =IF('_引擎'!B74,_zkfhzg,0) | E86: ='_引擎'!M74 | F86: ='_引擎'!O74 | G86: ='_引擎'!I74 | H86: ='_引擎'!AR74 | I86: ='_引擎'!AH74 | J86: ='_引擎'!AU74 | K86: ='_引擎'!AW74 | L86: ='_引擎'!AV74
B87: 9 | C87: ='_引擎'!F75 | D87: =IF('_引擎'!B75,_zkfhzg,0) | E87: ='_引擎'!M75 | F87: ='_引擎'!O75 | G87: ='_引擎'!I75 | H87: ='_引擎'!AR75 | I87: ='_引擎'!AH75 | J87: ='_引擎'!AU75 | K87: ='_引擎'!AW75 | L87: ='_引擎'!AV75
B88: 10 | C88: ='_引擎'!F76 | D88: =IF('_引擎'!B76,_zkfhzg,0) | E88: ='_引擎'!M76 | F88: ='_引擎'!O76 | G88: ='_引擎'!I76 | H88: ='_引擎'!AR76 | I88: ='_引擎'!AH76 | J88: ='_引擎'!AU76 | K88: ='_引擎'!AW76 | L88: ='_引擎'!AV76
B89: 11 | C89: ='_引擎'!F77 | D89: =IF('_引擎'!B77,_zkfhzg,0) | E89: ='_引擎'!M77 | F89: ='_引擎'!O77 | G89: ='_引擎'!I77 | H89: ='_引擎'!AR77 | I89: ='_引擎'!AH77 | J89: ='_引擎'!AU77 | K89: ='_引擎'!AW77 | L89: ='_引擎'!AV77
B90: 12 | C90: ='_引擎'!F78 | D90: =IF('_引擎'!B78,_zkfhzg,0) | E90: ='_引擎'!M78 | F90: ='_引擎'!O78 | G90: ='_引擎'!I78 | H90: ='_引擎'!AR78 | I90: ='_引擎'!AH78 | J90: ='_引擎'!AU78 | K90: ='_引擎'!AW78 | L90: ='_引擎'!AV78
... B103: 25 | C103: ='_引擎'!F91 | D103: =IF('_引擎'!B91,_zkfhzg,0) | E103: ='_引擎'!M91 | F103: ='_引擎'!O91 | G103: ='_引擎'!I91 | H103: ='_引擎'!AR91 | I103: ='_引擎'!AH91 | J103: ='_引擎'!AU91 | K103: ='_引擎'!AW91 | L103: ='_引擎'!AV91

Sheet _引擎
A1: 标量（引擎口径 2026-07；勿改）
A2: gen_avail | B2: =(_z35wsg*_zix1lp+_z4kl0k*_z98gva)*0.1
A3: gen_net | B3: =_zstij9*(1-_zvtsqd)
A4: self_use | B4: =IF((_zkrpcw="离网型"),MIN(_z6mxd8,_zs8nv3,_zftf5w),MIN(_z6mxd8,_zs8nv3))
A5: export | B5: =IF((_zkrpcw="离网型"),0,MAX(_zs8nv3-_zt11ik,0))
A6: downstream | B6: =IF((_zkrpcw="离网型"),0,MAX(_zftf5w-_zt11ik,0))
A7: ratio_self_gen | B7: =IF(_zstij9>0,_zt11ik/_zstij9,0)
A8: ratio_self_load | B8: =IF(_zftf5w>0,_zt11ik/_zftf5w,0)
A9: ratio_export_gen | B9: =IF(_zstij9>0,_z5gr99/_zstij9,0)
A10: base_cap_fee | B10: =IF((_z3xkci="按需量"),_zx32ce*_zzoaus*12,_zksy9m*_zbhssj*12)
A11: td_fee_cap | B11: =IF((_zkrpcw="离网型"),0,_zm650r/10000)
A12: td_fee_energy | B12: =IF((_zkrpcw="离网型"),0,IF((_zlj03i="单一容量制"),_zp8xhg*_z3m5k2*730*12*_zbhssj/10000,_zp8xhg*(_zsbxps+_zt11ik)))
A13: td_fee | B13: =_zektcz+_zdmffp
A14: sys_fee | B14: =IF((_zkrpcw="离网型"),0,_z5ctcx*_zsbxps)
A15: loss_fee | B15: =IF((_zkrpcw="离网型"),0,_zysee0*_zsbxps)
A16: cross_fee | B16: =IF((_zkrpcw="离网型"),0,_zw04od*_zsbxps)
A17: fund_base | B17: =IF((_zkrpcw="离网型"),_zt11ik,_zsbxps+IF((_zcshgi="下网+自用"),_zt11ik,0))
A18: fund_fee | B18: =_z78i0e*_ztkj9g
A19: cost_direct | B19: =_zk8d4f*_zt11ik
A20: cost_downstream | B20: =_zhw65s*_zsbxps
A21: user_total | B21: =_zqhyli+_za7fy7+_z928ab+_zqnyts+_z9r4dl+_ze6p1m+_zpzqxb
A22: user_avg_price | B22: =IF(_zftf5w>0,_zvy62p/_zftf5w,0)
A23: baseline | B23: =_zf2rqb*_zftf5w
A24: saving | B24: =_zfzfsr-_zvy62p
A25: saving_rate | B25: =IF(_zfzfsr>0,_zmorcm/_zfzfsr,0)
A26: green_avoid | B26: =_z8d2zq*_zt11ik
A27: capex_pv | B27: =_z35wsg*_zzvbgr*100
A28: capex_wind | B28: =_z4kl0k*_zzl39o*100
A29: capex_storage | B29: =_zjttpb*_zm9z4k*100
A30: depreciable_capex | B30: =_zkh06o+_z517d3+_z67r2o+_zbf04s
A31: capex_total | B31: =_zjqqhp+_z5sfpo
A32: idc_denom | B32: =1+_z1v75m*_zyywx7/2
A33: idc_qualifying_total | B33: =_zjqqhp*(1+_zyywx7/2)/_z3lk4m
A34: construction_interest | B34: =_zwp6v3-_zjqqhp
A35: capex_total_with_idc | B35: =_z1tt59+_zhc22k
A36: holiday_share | B36: =IF(_z1tt59>0,(_zkh06o+_z517d3)/_z1tt59,0)
A37: n_years | B37: =ROUND(_z7fj0w,0)
A38: equity | B38: =_z32w4e*_z1v75m
A39: loan | B39: =_z32w4e-_zn0hoh
A40: loan_years_r | B40: =ROUND(_z0ek84,0)
A41: pay | B41: =IF(_zyywx7=0,_zmqr32/_z2al7i,_zmqr32*_zyywx7/(1-(1+_zyywx7)^-_z2al7i))
A42: capex_net_all | B42: =_zjqqhp*(1-_zpnfsf)
A43: capex_net_eq | B43: =_z2nx0n+_zhc22k
A44: land_input_vat_capped | B44: =MIN(_zno06c,_z5sfpo*0.09/1.09)
A45: vat_pool0 | B45: =_zjqqhp*_zpnfsf+_zf6jpb
A46: dep_base_all | B46: =_z2nx0n*(1-_z52v2x)
A47: dep_base_eq | B47: =_z6o34p*(1-_z52v2x)
A48: dep_years_tax | B48: =ROUND(_zqudm6,0)
A49: dep_years_eff | B49: =MIN(_zk7d33,_zx5hja)
A50: dep_annual_all | B50: =_z9qfry/_zk7d33
A51: dep_annual_eq | B51: =_zsp8uj/_zk7d33
A52: land_tax_basis_all | B52: =MAX(0,_z5sfpo-_zf6jpb)
A53: land_tax_basis_eq | B53: =_zfraqw
A54: land_amort_years_tax | B54: =ROUND(_z7ukau,0)
A55: land_amort_years | B55: =MIN(_zvqyde,_zx5hja)
A56: land_amort_annual | B56: =IF(AND(_z5sfpo>0,_zvqyde>0),_zfraqw/_zvqyde,0)
A57: opex | B57: =_zjqqhp*(_zia8ld+_z5jv12)+_zl8371
A58: salvage_value_all | B58: =_z2nx0n*_z52v2x
A59: salvage_value_eq | B59: =_z6o34p*_z52v2x
A60: terminal_value_all | B60: =_z9itej+_z9qfry*MAX(0,_zk7d33-_zx5hja)/_zk7d33+_ze4vc7
A61: terminal_value_eq | B61: =_znvyxf+_zsp8uj*MAX(0,_zk7d33-_zx5hja)/_zk7d33+_ze4vc7
A62: replace_year_r | B62: =ROUND(_ziqmyk,0)
A65: 年份 | B65: 运营期内 | C65: 衰减系数 | D65: 自用电量 | E65: 上网电量 | F65: 含税收入 | G65: 不含税收入 | H65: 销项税 | I65: 更换支出 | J65: 更换进项税 | K65: 更换支出(不含税) | L65: 进项池期初 | M65: 实缴增值税 | N65: 进项池期末 | O65: 附加税费 | P65: 期初贷款余额 | Q65: 利息 | R65: 还本付息 | S65: 还本 | T65: 期末贷款余额 | U65: 折旧 | V65: 折旧·资本金 | W65: 土地摊销 | X65: 免减系数 | Y65: 有效税率系数 | Z65: EBT全投资 | AA65: 亏损池A·1年 | AB65: 亏损池A·2年 | AC65: 亏损池A·3年 | AD65: 亏损池A·4年 | AE65: 亏损池A·5年 | AF65: 亏损池A·当年弥补 | AG65: 应税所得·全投资 | AH65: 所得税·全投资 | AI65: EBT资本金 | AJ65: 亏损池E·1年 | AK65: 亏损池E·2年 | AL65: 亏损池E·3年 | AM65: 亏损池E·4年 | AN65: 亏损池E·5年 | AO65: 亏损池E·当年弥补 | AP65: 应税所得·资本金 | AQ65: 所得税·资本金 | AR65: 期末回收 | AS65: 期末回收·资本金 | AT65: 税前全投资净现金流 | AU65: 税后全投资净现金流 | AV65: 资本金净现金流 | AW65: 累计税后 | AX65: 转正标志 | AY65: 折现税后 | AZ65: 累计折现 | BA65: 转正标志动态 | BB65: 实发电量衰减后 | BC65: LCOE年成本 | BD65: 符号跟踪·税前 | BE65: 变号计数·税前 | BF65: 符号跟踪·税后 | BG65: 变号计数·税后 | BH65: 符号跟踪·资本金 | BI65: 变号计数·资本金
A66: 0 | B66: =FALSE | C66: 0 | D66: 0 | E66: 0 | F66: 0 | G66: 0 | H66: 0 | I66: 0 | J66: 0 | K66: 0 | L66: 0 | M66: 0 | N66: =_zh2s1v | O66: 0 | P66: 0 | Q66: 0 | R66: 0 | S66: 0 | T66: =_zmqr32 | U66: 0 | V66: 0 | W66: 0 | X66: 0 | Y66: 0 | Z66: 0 | AA66: 0 | AB66: 0 | AC66: 0 | AD66: 0 | AE66: 0 | AF66: 0 | AG66: 0 | AH66: 0 | AI66: 0 | AJ66: 0 | AK66: 0 | AL66: 0 | AM66: 0 | AN66: 0 | AO66: 0 | AP66: 0 | AQ66: 0 | AR66: 0 | AS66: 0 | AT66: =-_z1tt59 | AU66: =-_z1tt59 | AV66: =-_zn0hoh | AW66: =AU66 | AX66: 0 | AY66: =AU66 | AZ66: =AY66 | BA66: 0 | BB66: 0 | BC66: 0 | BD66: =SIGN(AT66) | BE66: 0 | BF66: =SIGN(AU66) | BG66: 0 | BH66: =SIGN(AV66) | BI66: 0
A67: 1 | B67: =AND(A67>=1,A67<=_zx5hja) | C67: =IF(B67,(1-_zg5443)^(A67-1),0) | D67: =_zt11ik*C67 | E67: =_z5gr99*C67 | F67: =_zk8d4f*D67+_zsw7bq*E67 | G67: =F67/(1+0.13) | H67: =F67-G67 | I67: =IF(AND(B67,A67=_ztfkfy),_z67r2o*_z0m7ys,0) | J67: =I67*0.13/(1+0.13) | K67: =I67-J67 | L67: =N66+J67 | M67: =MAX(0,H67-L67) | N67: =MAX(0,L67-H67) | O67: =M67*0.12 | P67: =T66 | Q67: =IF(AND(B67,A67<=_z2al7i),P67*_zyywx7,0) | R67: =IF(AND(B67,A67<=_z2al7i),_zgsfrl,0) | S67: =R67-Q67 | T67: =MAX(0,P67-S67) | U67: =IF(AND(B67,A67<=_zupe8l),_zb0m7l,0) | V67: =IF(AND(B67,A67<=_zupe8l),_zm1wss,0) | W67: =IF(AND(B67,A67<=_zhf3a4),_zdqt32,0) | X67: =IF((_zhsdpd="是"),IF(A67<=3,0,IF(A67<=6,0.5,1)),1) | Y67: =_zrzkf6*X67+(1-_zrzkf6) | Z67: =IF(B67,G67-_zkfhzg-O67-U67-W67-K67,0) | AA67: =MAX(0,-Z66) | AB67: =MIN(AA66,MAX(0,(AE66+AD66+AC66+AB66+AA66)-AF66)) | AC67: =MIN(AB66,MAX(0,(AE66+AD66+AC66+AB66)-AF66)) | AD67: =MIN(AC66,MAX(0,(AE66+AD66+AC66)-AF66)) | AE67: =MIN(AD66,MAX(0,(AE66+AD66)-AF66)) | AF67: =MIN(MAX(Z67,0),AA67+AB67+AC67+AD67+AE67) | AG67: =MAX(Z67,0)-AF67 | AH67: =AG67*_zs8hxw*Y67 | AI67: =IF(B67,G67-_zkfhzg-O67-V67-W67-K67-Q67,0) | AJ67: =MAX(0,-AI66) | AK67: =MIN(AJ66,MAX(0,(AN66+AM66+AL66+AK66+AJ66)-AO66)) | AL67: =MIN(AK66,MAX(0,(AN66+AM66+AL66+AK66)-AO66)) | AM67: =MIN(AL66,MAX(0,(AN66+AM66+AL66)-AO66)) | AN67: =MIN(AM66,MAX(0,(AN66+AM66)-AO66)) | AO67: =MIN(MAX(AI67,0),AJ67+AK67+AL67+AM67+AN67) | AP67: =MAX(AI67,0)-AO67 | AQ67: =AP67*_zs8hxw*Y67 | AR67: =IF(A67=_zx5hja,_zlajvq,0) | AS67: =IF(A67=_zx5hja,_zyh8pc,0) | AT67: =IF(B67,F67-_zkfhzg-M67-O67-I67+AR67,0) | AU67: =AT67-AH67 | AV67: =IF(B67,F67-_zkfhzg-M67-O67-I67-R67-AQ67+AS67-IF(AND(A67=_zx5hja,_z2al7i>_zx5hja),T67,0),0) | AW67: =AW66+AU67 | AX67: =IF(AND(AW66<0,AW67>=0,AU67>0),1,0) | AY67: =AU67/(1+_zawtbl)^A67 | AZ67: =AZ66+AY67 | BA67: =IF(AND(AZ66<0,AZ67>=0,AY67>0),1,0) | BB67: =_zs8nv3*C67 | BC67: =IF(B67,_zkfhzg+K67-AR67,0) | BD67: =IF(AT67=0,BD66,SIGN(AT67)) | BE67: =BE66+IF(OR(AT67=0,BD66=0),0,IF(SIGN(AT67)<>BD66,1,0)) | BF67: =IF(AU67=0,BF66,SIGN(AU67)) | BG67: =BG66+IF(OR(AU67=0,BF66=0),0,IF(SIGN(AU67)<>BF66,1,0)) | BH67: =IF(AV67=0,BH66,SIGN(AV67)) | BI67: =BI66+IF(OR(AV67=0,BH66=0),0,IF(SIGN(AV67)<>BH66,1,0))
A68: 2 | B68: =AND(A68>=1,A68<=_zx5hja) | C68: =IF(B68,(1-_zg5443)^(A68-1),0) | D68: =_zt11ik*C68 | E68: =_z5gr99*C68 | F68: =_zk8d4f*D68+_zsw7bq*E68 | G68: =F68/(1+0.13) | H68: =F68-G68 | I68: =IF(AND(B68,A68=_ztfkfy),_z67r2o*_z0m7ys,0) | J68: =I68*0.13/(1+0.13) | K68: =I68-J68 | L68: =N67+J68 | M68: =MAX(0,H68-L68) | N68: =MAX(0,L68-H68) | O68: =M68*0.12 | P68: =T67 | Q68: =IF(AND(B68,A68<=_z2al7i),P68*_zyywx7,0) | R68: =IF(AND(B68,A68<=_z2al7i),_zgsfrl,0) | S68: =R68-Q68 | T68: =MAX(0,P68-S68) | U68: =IF(AND(B68,A68<=_zupe8l),_zb0m7l,0) | V68: =IF(AND(B68,A68<=_zupe8l),_zm1wss,0) | W68: =IF(AND(B68,A68<=_zhf3a4),_zdqt32,0) | X68: =IF((_zhsdpd="是"),IF(A68<=3,0,IF(A68<=6,0.5,1)),1) | Y68: =_zrzkf6*X68+(1-_zrzkf6) | Z68: =IF(B68,G68-_zkfhzg-O68-U68-W68-K68,0) | AA68: =MAX(0,-Z67) | AB68: =MIN(AA67,MAX(0,(AE67+AD67+AC67+AB67+AA67)-AF67)) | AC68: =MIN(AB67,MAX(0,(AE67+AD67+AC67+AB67)-AF67)) | AD68: =MIN(AC67,MAX(0,(AE67+AD67+AC67)-AF67)) | AE68: =MIN(AD67,MAX(0,(AE67+AD67)-AF67)) | AF68: =MIN(MAX(Z68,0),AA68+AB68+AC68+AD68+AE68) | AG68: =MAX(Z68,0)-AF68 | AH68: =AG68*_zs8hxw*Y68 | AI68: =IF(B68,G68-_zkfhzg-O68-V68-W68-K68-Q68,0) | AJ68: =MAX(0,-AI67) | AK68: =MIN(AJ67,MAX(0,(AN67+AM67+AL67+AK67+AJ67)-AO67)) | AL68: =MIN(AK67,MAX(0,(AN67+AM67+AL67+AK67)-AO67)) | AM68: =MIN(AL67,MAX(0,(AN67+AM67+AL67)-AO67)) | AN68: =MIN(AM67,MAX(0,(AN67+AM67)-AO67)) | AO68: =MIN(MAX(AI68,0),AJ68+AK68+AL68+AM68+AN68) | AP68: =MAX(AI68,0)-AO68 | AQ68: =AP68*_zs8hxw*Y68 | AR68: =IF(A68=_zx5hja,_zlajvq,0) | AS68: =IF(A68=_zx5hja,_zyh8pc,0) | AT68: =IF(B68,F68-_zkfhzg-M68-O68-I68+AR68,0) | AU68: =AT68-AH68 | AV68: =IF(B68,F68-_zkfhzg-M68-O68-I68-R68-AQ68+AS68-IF(AND(A68=_zx5hja,_z2al7i>_zx5hja),T68,0),0) | AW68: =AW67+AU68 | AX68: =IF(AND(AW67<0,AW68>=0,AU68>0),1,0) | AY68: =AU68/(1+_zawtbl)^A68 | AZ68: =AZ67+AY68 | BA68: =IF(AND(AZ67<0,AZ68>=0,AY68>0),1,0) | BB68: =_zs8nv3*C68 | BC68: =IF(B68,_zkfhzg+K68-AR68,0) | BD68: =IF(AT68=0,BD67,SIGN(AT68)) | BE68: =BE67+IF(OR(AT68=0,BD67=0),0,IF(SIGN(AT68)<>BD67,1,0)) | BF68: =IF(AU68=0,BF67,SIGN(AU68)) | BG68: =BG67+IF(OR(AU68=0,BF67=0),0,IF(SIGN(AU68)<>BF67,1,0)) | BH68: =IF(AV68=0,BH67,SIGN(AV68)) | BI68: =BI67+IF(OR(AV68=0,BH67=0),0,IF(SIGN(AV68)<>BH67,1,0))
A69: 3 | B69: =AND(A69>=1,A69<=_zx5hja) | C69: =IF(B69,(1-_zg5443)^(A69-1),0) | D69: =_zt11ik*C69 | E69: =_z5gr99*C69 | F69: =_zk8d4f*D69+_zsw7bq*E69 | G69: =F69/(1+0.13) | H69: =F69-G69 | I69: =IF(AND(B69,A69=_ztfkfy),_z67r2o*_z0m7ys,0) | J69: =I69*0.13/(1+0.13) | K69: =I69-J69 | L69: =N68+J69 | M69: =MAX(0,H69-L69) | N69: =MAX(0,L69-H69) | O69: =M69*0.12 | P69: =T68 | Q69: =IF(AND(B69,A69<=_z2al7i),P69*_zyywx7,0) | R69: =IF(AND(B69,A69<=_z2al7i),_zgsfrl,0) | S69: =R69-Q69 | T69: =MAX(0,P69-S69) | U69: =IF(AND(B69,A69<=_zupe8l),_zb0m7l,0) | V69: =IF(AND(B69,A69<=_zupe8l),_zm1wss,0) | W69: =IF(AND(B69,A69<=_zhf3a4),_zdqt32,0) | X69: =IF((_zhsdpd="是"),IF(A69<=3,0,IF(A69<=6,0.5,1)),1) | Y69: =_zrzkf6*X69+(1-_zrzkf6) | Z69: =IF(B69,G69-_zkfhzg-O69-U69-W69-K69,0) | AA69: =MAX(0,-Z68) | AB69: =MIN(AA68,MAX(0,(AE68+AD68+AC68+AB68+AA68)-AF68)) | AC69: =MIN(AB68,MAX(0,(AE68+AD68+AC68+AB68)-AF68)) | AD69: =MIN(AC68,MAX(0,(AE68+AD68+AC68)-AF68)) | AE69: =MIN(AD68,MAX(0,(AE68+AD68)-AF68)) | AF69: =MIN(MAX(Z69,0),AA69+AB69+AC69+AD69+AE69) | AG69: =MAX(Z69,0)-AF69 | AH69: =AG69*_zs8hxw*Y69 | AI69: =IF(B69,G69-_zkfhzg-O69-V69-W69-K69-Q69,0) | AJ69: =MAX(0,-AI68) | AK69: =MIN(AJ68,MAX(0,(AN68+AM68+AL68+AK68+AJ68)-AO68)) | AL69: =MIN(AK68,MAX(0,(AN68+AM68+AL68+AK68)-AO68)) | AM69: =MIN(AL68,MAX(0,(AN68+AM68+AL68)-AO68)) | AN69: =MIN(AM68,MAX(0,(AN68+AM68)-AO68)) | AO69: =MIN(MAX(AI69,0),AJ69+AK69+AL69+AM69+AN69) | AP69: =MAX(AI69,0)-AO69 | AQ69: =AP69*_zs8hxw*Y69 | AR69: =IF(A69=_zx5hja,_zlajvq,0) | AS69: =IF(A69=_zx5hja,_zyh8pc,0) | AT69: =IF(B69,F69-_zkfhzg-M69-O69-I69+AR69,0) | AU69: =AT69-AH69 | AV69: =IF(B69,F69-_zkfhzg-M69-O69-I69-R69-AQ69+AS69-IF(AND(A69=_zx5hja,_z2al7i>_zx5hja),T69,0),0) | AW69: =AW68+AU69 | AX69: =IF(AND(AW68<0,AW69>=0,AU69>0),1,0) | AY69: =AU69/(1+_zawtbl)^A69 | AZ69: =AZ68+AY69 | BA69: =IF(AND(AZ68<0,AZ69>=0,AY69>0),1,0) | BB69: =_zs8nv3*C69 | BC69: =IF(B69,_zkfhzg+K69-AR69,0) | BD69: =IF(AT69=0,BD68,SIGN(AT69)) | BE69: =BE68+IF(OR(AT69=0,BD68=0),0,IF(SIGN(AT69)<>BD68,1,0)) | BF69: =IF(AU69=0,BF68,SIGN(AU69)) | BG69: =BG68+IF(OR(AU69=0,BF68=0),0,IF(SIGN(AU69)<>BF68,1,0)) | BH69: =IF(AV69=0,BH68,SIGN(AV69)) | BI69: =BI68+IF(OR(AV69=0,BH68=0),0,IF(SIGN(AV69)<>BH68,1,0))
A70: 4 | B70: =AND(A70>=1,A70<=_zx5hja) | C70: =IF(B70,(1-_zg5443)^(A70-1),0) | D70: =_zt11ik*C70 | E70: =_z5gr99*C70 | F70: =_zk8d4f*D70+_zsw7bq*E70 | G70: =F70/(1+0.13) | H70: =F70-G70 | I70: =IF(AND(B70,A70=_ztfkfy),_z67r2o*_z0m7ys,0) | J70: =I70*0.13/(1+0.13) | K70: =I70-J70 | L70: =N69+J70 | M70: =MAX(0,H70-L70) | N70: =MAX(0,L70-H70) | O70: =M70*0.12 | P70: =T69 | Q70: =IF(AND(B70,A70<=_z2al7i),P70*_zyywx7,0) | R70: =IF(AND(B70,A70<=_z2al7i),_zgsfrl,0) | S70: =R70-Q70 | T70: =MAX(0,P70-S70) | U70: =IF(AND(B70,A70<=_zupe8l),_zb0m7l,0) | V70: =IF(AND(B70,A70<=_zupe8l),_zm1wss,0) | W70: =IF(AND(B70,A70<=_zhf3a4),_zdqt32,0) | X70: =IF((_zhsdpd="是"),IF(A70<=3,0,IF(A70<=6,0.5,1)),1) | Y70: =_zrzkf6*X70+(1-_zrzkf6) | Z70: =IF(B70,G70-_zkfhzg-O70-U70-W70-K70,0) | AA70: =MAX(0,-Z69) | AB70: =MIN(AA69,MAX(0,(AE69+AD69+AC69+AB69+AA69)-AF69)) | AC70: =MIN(AB69,MAX(0,(AE69+AD69+AC69+AB69)-AF69)) | AD70: =MIN(AC69,MAX(0,(AE69+AD69+AC69)-AF69)) | AE70: =MIN(AD69,MAX(0,(AE69+AD69)-AF69)) | AF70: =MIN(MAX(Z70,0),AA70+AB70+AC70+AD70+AE70) | AG70: =MAX(Z70,0)-AF70 | AH70: =AG70*_zs8hxw*Y70 | AI70: =IF(B70,G70-_zkfhzg-O70-V70-W70-K70-Q70,0) | AJ70: =MAX(0,-AI69) | AK70: =MIN(AJ69,MAX(0,(AN69+AM69+AL69+AK69+AJ69)-AO69)) | AL70: =MIN(AK69,MAX(0,(AN69+AM69+AL69+AK69)-AO69)) | AM70: =MIN(AL69,MAX(0,(AN69+AM69+AL69)-AO69)) | AN70: =MIN(AM69,MAX(0,(AN69+AM69)-AO69)) | AO70: =MIN(MAX(AI70,0),AJ70+AK70+AL70+AM70+AN70) | AP70: =MAX(AI70,0)-AO70 | AQ70: =AP70*_zs8hxw*Y70 | AR70: =IF(A70=_zx5hja,_zlajvq,0) | AS70: =IF(A70=_zx5hja,_zyh8pc,0) | AT70: =IF(B70,F70-_zkfhzg-M70-O70-I70+AR70,0) | AU70: =AT70-AH70 | AV70: =IF(B70,F70-_zkfhzg-M70-O70-I70-R70-AQ70+AS70-IF(AND(A70=_zx5hja,_z2al7i>_zx5hja),T70,0),0) | AW70: =AW69+AU70 | AX70: =IF(AND(AW69<0,AW70>=0,AU70>0),1,0) | AY70: =AU70/(1+_zawtbl)^A70 | AZ70: =AZ69+AY70 | BA70: =IF(AND(AZ69<0,AZ70>=0,AY70>0),1,0) | BB70: =_zs8nv3*C70 | BC70: =IF(B70,_zkfhzg+K70-AR70,0) | BD70: =IF(AT70=0,BD69,SIGN(AT70)) | BE70: =BE69+IF(OR(AT70=0,BD69=0),0,IF(SIGN(AT70)<>BD69,1,0)) | BF70: =IF(AU70=0,BF69,SIGN(AU70)) | BG70: =BG69+IF(OR(AU70=0,BF69=0),0,IF(SIGN(AU70)<>BF69,1,0)) | BH70: =IF(AV70=0,BH69,SIGN(AV70)) | BI70: =BI69+IF(OR(AV70=0,BH69=0),0,IF(SIGN(AV70)<>BH69,1,0))
A71: 5 | B71: =AND(A71>=1,A71<=_zx5hja) | C71: =IF(B71,(1-_zg5443)^(A71-1),0) | D71: =_zt11ik*C71 | E71: =_z5gr99*C71 | F71: =_zk8d4f*D71+_zsw7bq*E71 | G71: =F71/(1+0.13) | H71: =F71-G71 | I71: =IF(AND(B71,A71=_ztfkfy),_z67r2o*_z0m7ys,0) | J71: =I71*0.13/(1+0.13) | K71: =I71-J71 | L71: =N70+J71 | M71: =MAX(0,H71-L71) | N71: =MAX(0,L71-H71) | O71: =M71*0.12 | P71: =T70 | Q71: =IF(AND(B71,A71<=_z2al7i),P71*_zyywx7,0) | R71: =IF(AND(B71,A71<=_z2al7i),_zgsfrl,0) | S71: =R71-Q71 | T71: =MAX(0,P71-S71) | U71: =IF(AND(B71,A71<=_zupe8l),_zb0m7l,0) | V71: =IF(AND(B71,A71<=_zupe8l),_zm1wss,0) | W71: =IF(AND(B71,A71<=_zhf3a4),_zdqt32,0) | X71: =IF((_zhsdpd="是"),IF(A71<=3,0,IF(A71<=6,0.5,1)),1) | Y71: =_zrzkf6*X71+(1-_zrzkf6) | Z71: =IF(B71,G71-_zkfhzg-O71-U71-W71-K71,0) | AA71: =MAX(0,-Z70) | AB71: =MIN(AA70,MAX(0,(AE70+AD70+AC70+AB70+AA70)-AF70)) | AC71: =MIN(AB70,MAX(0,(AE70+AD70+AC70+AB70)-AF70)) | AD71: =MIN(AC70,MAX(0,(AE70+AD70+AC70)-AF70)) | AE71: =MIN(AD70,MAX(0,(AE70+AD70)-AF70)) | AF71: =MIN(MAX(Z71,0),AA71+AB71+AC71+AD71+AE71) | AG71: =MAX(Z71,0)-AF71 | AH71: =AG71*_zs8hxw*Y71 | AI71: =IF(B71,G71-_zkfhzg-O71-V71-W71-K71-Q71,0) | AJ71: =MAX(0,-AI70) | AK71: =MIN(AJ70,MAX(0,(AN70+AM70+AL70+AK70+AJ70)-AO70)) | AL71: =MIN(AK70,MAX(0,(AN70+AM70+AL70+AK70)-AO70)) | AM71: =MIN(AL70,MAX(0,(AN70+AM70+AL70)-AO70)) | AN71: =MIN(AM70,MAX(0,(AN70+AM70)-AO70)) | AO71: =MIN(MAX(AI71,0),AJ71+AK71+AL71+AM71+AN71) | AP71: =MAX(AI71,0)-AO71 | AQ71: =AP71*_zs8hxw*Y71 | AR71: =IF(A71=_zx5hja,_zlajvq,0) | AS71: =IF(A71=_zx5hja,_zyh8pc,0) | AT71: =IF(B71,F71-_zkfhzg-M71-O71-I71+AR71,0) | AU71: =AT71-AH71 | AV71: =IF(B71,F71-_zkfhzg-M71-O71-I71-R71-AQ71+AS71-IF(AND(A71=_zx5hja,_z2al7i>_zx5hja),T71,0),0) | AW71: =AW70+AU71 | AX71: =IF(AND(AW70<0,AW71>=0,AU71>0),1,0) | AY71: =AU71/(1+_zawtbl)^A71 | AZ71: =AZ70+AY71 | BA71: =IF(AND(AZ70<0,AZ71>=0,AY71>0),1,0) | BB71: =_zs8nv3*C71 | BC71: =IF(B71,_zkfhzg+K71-AR71,0) | BD71: =IF(AT71=0,BD70,SIGN(AT71)) | BE71: =BE70+IF(OR(AT71=0,BD70=0),0,IF(SIGN(AT71)<>BD70,1,0)) | BF71: =IF(AU71=0,BF70,SIGN(AU71)) | BG71: =BG70+IF(OR(AU71=0,BF70=0),0,IF(SIGN(AU71)<>BF70,1,0)) | BH71: =IF(AV71=0,BH70,SIGN(AV71)) | BI71: =BI70+IF(OR(AV71=0,BH70=0),0,IF(SIGN(AV71)<>BH70,1,0))
A72: 6 | B72: =AND(A72>=1,A72<=_zx5hja) | C72: =IF(B72,(1-_zg5443)^(A72-1),0) | D72: =_zt11ik*C72 | E72: =_z5gr99*C72 | F72: =_zk8d4f*D72+_zsw7bq*E72 | G72: =F72/(1+0.13) | H72: =F72-G72 | I72: =IF(AND(B72,A72=_ztfkfy),_z67r2o*_z0m7ys,0) | J72: =I72*0.13/(1+0.13) | K72: =I72-J72 | L72: =N71+J72 | M72: =MAX(0,H72-L72) | N72: =MAX(0,L72-H72) | O72: =M72*0.12 | P72: =T71 | Q72: =IF(AND(B72,A72<=_z2al7i),P72*_zyywx7,0) | R72: =IF(AND(B72,A72<=_z2al7i),_zgsfrl,0) | S72: =R72-Q72 | T72: =MAX(0,P72-S72) | U72: =IF(AND(B72,A72<=_zupe8l),_zb0m7l,0) | V72: =IF(AND(B72,A72<=_zupe8l),_zm1wss,0) | W72: =IF(AND(B72,A72<=_zhf3a4),_zdqt32,0) | X72: =IF((_zhsdpd="是"),IF(A72<=3,0,IF(A72<=6,0.5,1)),1) | Y72: =_zrzkf6*X72+(1-_zrzkf6) | Z72: =IF(B72,G72-_zkfhzg-O72-U72-W72-K72,0) | AA72: =MAX(0,-Z71) | AB72: =MIN(AA71,MAX(0,(AE71+AD71+AC71+AB71+AA71)-AF71)) | AC72: =MIN(AB71,MAX(0,(AE71+AD71+AC71+AB71)-AF71)) | AD72: =MIN(AC71,MAX(0,(AE71+AD71+AC71)-AF71)) | AE72: =MIN(AD71,MAX(0,(AE71+AD71)-AF71)) | AF72: =MIN(MAX(Z72,0),AA72+AB72+AC72+AD72+AE72) | AG72: =MAX(Z72,0)-AF72 | AH72: =AG72*_zs8hxw*Y72 | AI72: =IF(B72,G72-_zkfhzg-O72-V72-W72-K72-Q72,0) | AJ72: =MAX(0,-AI71) | AK72: =MIN(AJ71,MAX(0,(AN71+AM71+AL71+AK71+AJ71)-AO71)) | AL72: =MIN(AK71,MAX(0,(AN71+AM71+AL71+AK71)-AO71)) | AM72: =MIN(AL71,MAX(0,(AN71+AM71+AL71)-AO71)) | AN72: =MIN(AM71,MAX(0,(AN71+AM71)-AO71)) | AO72: =MIN(MAX(AI72,0),AJ72+AK72+AL72+AM72+AN72) | AP72: =MAX(AI72,0)-AO72 | AQ72: =AP72*_zs8hxw*Y72 | AR72: =IF(A72=_zx5hja,_zlajvq,0) | AS72: =IF(A72=_zx5hja,_zyh8pc,0) | AT72: =IF(B72,F72-_zkfhzg-M72-O72-I72+AR72,0) | AU72: =AT72-AH72 | AV72: =IF(B72,F72-_zkfhzg-M72-O72-I72-R72-AQ72+AS72-IF(AND(A72=_zx5hja,_z2al7i>_zx5hja),T72,0),0) | AW72: =AW71+AU72 | AX72: =IF(AND(AW71<0,AW72>=0,AU72>0),1,0) | AY72: =AU72/(1+_zawtbl)^A72 | AZ72: =AZ71+AY72 | BA72: =IF(AND(AZ71<0,AZ72>=0,AY72>0),1,0) | BB72: =_zs8nv3*C72 | BC72: =IF(B72,_zkfhzg+K72-AR72,0) | BD72: =IF(AT72=0,BD71,SIGN(AT72)) | BE72: =BE71+IF(OR(AT72=0,BD71=0),0,IF(SIGN(AT72)<>BD71,1,0)) | BF72: =IF(AU72=0,BF71,SIGN(AU72)) | BG72: =BG71+IF(OR(AU72=0,BF71=0),0,IF(SIGN(AU72)<>BF71,1,0)) | BH72: =IF(AV72=0,BH71,SIGN(AV72)) | BI72: =BI71+IF(OR(AV72=0,BH71=0),0,IF(SIGN(AV72)<>BH71,1,0))
A73: 7 | B73: =AND(A73>=1,A73<=_zx5hja) | C73: =IF(B73,(1-_zg5443)^(A73-1),0) | D73: =_zt11ik*C73 | E73: =_z5gr99*C73 | F73: =_zk8d4f*D73+_zsw7bq*E73 | G73: =F73/(1+0.13) | H73: =F73-G73 | I73: =IF(AND(B73,A73=_ztfkfy),_z67r2o*_z0m7ys,0) | J73: =I73*0.13/(1+0.13) | K73: =I73-J73 | L73: =N72+J73 | M73: =MAX(0,H73-L73) | N73: =MAX(0,L73-H73) | O73: =M73*0.12 | P73: =T72 | Q73: =IF(AND(B73,A73<=_z2al7i),P73*_zyywx7,0) | R73: =IF(AND(B73,A73<=_z2al7i),_zgsfrl,0) | S73: =R73-Q73 | T73: =MAX(0,P73-S73) | U73: =IF(AND(B73,A73<=_zupe8l),_zb0m7l,0) | V73: =IF(AND(B73,A73<=_zupe8l),_zm1wss,0) | W73: =IF(AND(B73,A73<=_zhf3a4),_zdqt32,0) | X73: =IF((_zhsdpd="是"),IF(A73<=3,0,IF(A73<=6,0.5,1)),1) | Y73: =_zrzkf6*X73+(1-_zrzkf6) | Z73: =IF(B73,G73-_zkfhzg-O73-U73-W73-K73,0) | AA73: =MAX(0,-Z72) | AB73: =MIN(AA72,MAX(0,(AE72+AD72+AC72+AB72+AA72)-AF72)) | AC73: =MIN(AB72,MAX(0,(AE72+AD72+AC72+AB72)-AF72)) | AD73: =MIN(AC72,MAX(0,(AE72+AD72+AC72)-AF72)) | AE73: =MIN(AD72,MAX(0,(AE72+AD72)-AF72)) | AF73: =MIN(MAX(Z73,0),AA73+AB73+AC73+AD73+AE73) | AG73: =MAX(Z73,0)-AF73 | AH73: =AG73*_zs8hxw*Y73 | AI73: =IF(B73,G73-_zkfhzg-O73-V73-W73-K73-Q73,0) | AJ73: =MAX(0,-AI72) | AK73: =MIN(AJ72,MAX(0,(AN72+AM72+AL72+AK72+AJ72)-AO72)) | AL73: =MIN(AK72,MAX(0,(AN72+AM72+AL72+AK72)-AO72)) | AM73: =MIN(AL72,MAX(0,(AN72+AM72+AL72)-AO72)) | AN73: =MIN(AM72,MAX(0,(AN72+AM72)-AO72)) | AO73: =MIN(MAX(AI73,0),AJ73+AK73+AL73+AM73+AN73) | AP73: =MAX(AI73,0)-AO73 | AQ73: =AP73*_zs8hxw*Y73 | AR73: =IF(A73=_zx5hja,_zlajvq,0) | AS73: =IF(A73=_zx5hja,_zyh8pc,0) | AT73: =IF(B73,F73-_zkfhzg-M73-O73-I73+AR73,0) | AU73: =AT73-AH73 | AV73: =IF(B73,F73-_zkfhzg-M73-O73-I73-R73-AQ73+AS73-IF(AND(A73=_zx5hja,_z2al7i>_zx5hja),T73,0),0) | AW73: =AW72+AU73 | AX73: =IF(AND(AW72<0,AW73>=0,AU73>0),1,0) | AY73: =AU73/(1+_zawtbl)^A73 | AZ73: =AZ72+AY73 | BA73: =IF(AND(AZ72<0,AZ73>=0,AY73>0),1,0) | BB73: =_zs8nv3*C73 | BC73: =IF(B73,_zkfhzg+K73-AR73,0) | BD73: =IF(AT73=0,BD72,SIGN(AT73)) | BE73: =BE72+IF(OR(AT73=0,BD72=0),0,IF(SIGN(AT73)<>BD72,1,0)) | BF73: =IF(AU73=0,BF72,SIGN(AU73)) | BG73: =BG72+IF(OR(AU73=0,BF72=0),0,IF(SIGN(AU73)<>BF72,1,0)) | BH73: =IF(AV73=0,BH72,SIGN(AV73)) | BI73: =BI72+IF(OR(AV73=0,BH72=0),0,IF(SIGN(AV73)<>BH72,1,0))
A74: 8 | B74: =AND(A74>=1,A74<=_zx5hja) | C74: =IF(B74,(1-_zg5443)^(A74-1),0) | D74: =_zt11ik*C74 | E74: =_z5gr99*C74 | F74: =_zk8d4f*D74+_zsw7bq*E74 | G74: =F74/(1+0.13) | H74: =F74-G74 | I74: =IF(AND(B74,A74=_ztfkfy),_z67r2o*_z0m7ys,0) | J74: =I74*0.13/(1+0.13) | K74: =I74-J74 | L74: =N73+J74 | M74: =MAX(0,H74-L74) | N74: =MAX(0,L74-H74) | O74: =M74*0.12 | P74: =T73 | Q74: =IF(AND(B74,A74<=_z2al7i),P74*_zyywx7,0) | R74: =IF(AND(B74,A74<=_z2al7i),_zgsfrl,0) | S74: =R74-Q74 | T74: =MAX(0,P74-S74) | U74: =IF(AND(B74,A74<=_zupe8l),_zb0m7l,0) | V74: =IF(AND(B74,A74<=_zupe8l),_zm1wss,0) | W74: =IF(AND(B74,A74<=_zhf3a4),_zdqt32,0) | X74: =IF((_zhsdpd="是"),IF(A74<=3,0,IF(A74<=6,0.5,1)),1) | Y74: =_zrzkf6*X74+(1-_zrzkf6) | Z74: =IF(B74,G74-_zkfhzg-O74-U74-W74-K74,0) | AA74: =MAX(0,-Z73) | AB74: =MIN(AA73,MAX(0,(AE73+AD73+AC73+AB73+AA73)-AF73)) | AC74: =MIN(AB73,MAX(0,(AE73+AD73+AC73+AB73)-AF73)) | AD74: =MIN(AC73,MAX(0,(AE73+AD73+AC73)-AF73)) | AE74: =MIN(AD73,MAX(0,(AE73+AD73)-AF73)) | AF74: =MIN(MAX(Z74,0),AA74+AB74+AC74+AD74+AE74) | AG74: =MAX(Z74,0)-AF74 | AH74: =AG74*_zs8hxw*Y74 | AI74: =IF(B74,G74-_zkfhzg-O74-V74-W74-K74-Q74,0) | AJ74: =MAX(0,-AI73) | AK74: =MIN(AJ73,MAX(0,(AN73+AM73+AL73+AK73+AJ73)-AO73)) | AL74: =MIN(AK73,MAX(0,(AN73+AM73+AL73+AK73)-AO73)) | AM74: =MIN(AL73,MAX(0,(AN73+AM73+AL73)-AO73)) | AN74: =MIN(AM73,MAX(0,(AN73+AM73)-AO73)) | AO74: =MIN(MAX(AI74,0),AJ74+AK74+AL74+AM74+AN74) | AP74: =MAX(AI74,0)-AO74 | AQ74: =AP74*_zs8hxw*Y74 | AR74: =IF(A74=_zx5hja,_zlajvq,0) | AS74: =IF(A74=_zx5hja,_zyh8pc,0) | AT74: =IF(B74,F74-_zkfhzg-M74-O74-I74+AR74,0) | AU74: =AT74-AH74 | AV74: =IF(B74,F74-_zkfhzg-M74-O74-I74-R74-AQ74+AS74-IF(AND(A74=_zx5hja,_z2al7i>_zx5hja),T74,0),0) | AW74: =AW73+AU74 | AX74: =IF(AND(AW73<0,AW74>=0,AU74>0),1,0) | AY74: =AU74/(1+_zawtbl)^A74 | AZ74: =AZ73+AY74 | BA74: =IF(AND(AZ73<0,AZ74>=0,AY74>0),1,0) | BB74: =_zs8nv3*C74 | BC74: =IF(B74,_zkfhzg+K74-AR74,0) | BD74: =IF(AT74=0,BD73,SIGN(AT74)) | BE74: =BE73+IF(OR(AT74=0,BD73=0),0,IF(SIGN(AT74)<>BD73,1,0)) | BF74: =IF(AU74=0,BF73,SIGN(AU74)) | BG74: =BG73+IF(OR(AU74=0,BF73=0),0,IF(SIGN(AU74)<>BF73,1,0)) | BH74: =IF(AV74=0,BH73,SIGN(AV74)) | BI74: =BI73+IF(OR(AV74=0,BH73=0),0,IF(SIGN(AV74)<>BH73,1,0))
A75: 9 | B75: =AND(A75>=1,A75<=_zx5hja) | C75: =IF(B75,(1-_zg5443)^(A75-1),0) | D75: =_zt11ik*C75 | E75: =_z5gr99*C75 | F75: =_zk8d4f*D75+_zsw7bq*E75 | G75: =F75/(1+0.13) | H75: =F75-G75 | I75: =IF(AND(B75,A75=_ztfkfy),_z67r2o*_z0m7ys,0) | J75: =I75*0.13/(1+0.13) | K75: =I75-J75 | L75: =N74+J75 | M75: =MAX(0,H75-L75) | N75: =MAX(0,L75-H75) | O75: =M75*0.12 | P75: =T74 | Q75: =IF(AND(B75,A75<=_z2al7i),P75*_zyywx7,0) | R75: =IF(AND(B75,A75<=_z2al7i),_zgsfrl,0) | S75: =R75-Q75 | T75: =MAX(0,P75-S75) | U75: =IF(AND(B75,A75<=_zupe8l),_zb0m7l,0) | V75: =IF(AND(B75,A75<=_zupe8l),_zm1wss,0) | W75: =IF(AND(B75,A75<=_zhf3a4),_zdqt32,0) | X75: =IF((_zhsdpd="是"),IF(A75<=3,0,IF(A75<=6,0.5,1)),1) | Y75: =_zrzkf6*X75+(1-_zrzkf6) | Z75: =IF(B75,G75-_zkfhzg-O75-U75-W75-K75,0) | AA75: =MAX(0,-Z74) | AB75: =MIN(AA74,MAX(0,(AE74+AD74+AC74+AB74+AA74)-AF74)) | AC75: =MIN(AB74,MAX(0,(AE74+AD74+AC74+AB74)-AF74)) | AD75: =MIN(AC74,MAX(0,(AE74+AD74+AC74)-AF74)) | AE75: =MIN(AD74,MAX(0,(AE74+AD74)-AF74)) | AF75: =MIN(MAX(Z75,0),AA75+AB75+AC75+AD75+AE75) | AG75: =MAX(Z75,0)-AF75 | AH75: =AG75*_zs8hxw*Y75 | AI75: =IF(B75,G75-_zkfhzg-O75-V75-W75-K75-Q75,0) | AJ75: =MAX(0,-AI74) | AK75: =MIN(AJ74,MAX(0,(AN74+AM74+AL74+AK74+AJ74)-AO74)) | AL75: =MIN(AK74,MAX(0,(AN74+AM74+AL74+AK74)-AO74)) | AM75: =MIN(AL74,MAX(0,(AN74+AM74+AL74)-AO74)) | AN75: =MIN(AM74,MAX(0,(AN74+AM74)-AO74)) | AO75: =MIN(MAX(AI75,0),AJ75+AK75+AL75+AM75+AN75) | AP75: =MAX(AI75,0)-AO75 | AQ75: =AP75*_zs8hxw*Y75 | AR75: =IF(A75=_zx5hja,_zlajvq,0) | AS75: =IF(A75=_zx5hja,_zyh8pc,0) | AT75: =IF(B75,F75-_zkfhzg-M75-O75-I75+AR75,0) | AU75: =AT75-AH75 | AV75: =IF(B75,F75-_zkfhzg-M75-O75-I75-R75-AQ75+AS75-IF(AND(A75=_zx5hja,_z2al7i>_zx5hja),T75,0),0) | AW75: =AW74+AU75 | AX75: =IF(AND(AW74<0,AW75>=0,AU75>0),1,0) | AY75: =AU75/(1+_zawtbl)^A75 | AZ75: =AZ74+AY75 | BA75: =IF(AND(AZ74<0,AZ75>=0,AY75>0),1,0) | BB75: =_zs8nv3*C75 | BC75: =IF(B75,_zkfhzg+K75-AR75,0) | BD75: =IF(AT75=0,BD74,SIGN(AT75)) | BE75: =BE74+IF(OR(AT75=0,BD74=0),0,IF(SIGN(AT75)<>BD74,1,0)) | BF75: =IF(AU75=0,BF74,SIGN(AU75)) | BG75: =BG74+IF(OR(AU75=0,BF74=0),0,IF(SIGN(AU75)<>BF74,1,0)) | BH75: =IF(AV75=0,BH74,SIGN(AV75)) | BI75: =BI74+IF(OR(AV75=0,BH74=0),0,IF(SIGN(AV75)<>BH74,1,0))
A76: 10 | B76: =AND(A76>=1,A76<=_zx5hja) | C76: =IF(B76,(1-_zg5443)^(A76-1),0) | D76: =_zt11ik*C76 | E76: =_z5gr99*C76 | F76: =_zk8d4f*D76+_zsw7bq*E76 | G76: =F76/(1+0.13) | H76: =F76-G76 | I76: =IF(AND(B76,A76=_ztfkfy),_z67r2o*_z0m7ys,0) | J76: =I76*0.13/(1+0.13) | K76: =I76-J76 | L76: =N75+J76 | M76: =MAX(0,H76-L76) | N76: =MAX(0,L76-H76) | O76: =M76*0.12 | P76: =T75 | Q76: =IF(AND(B76,A76<=_z2al7i),P76*_zyywx7,0) | R76: =IF(AND(B76,A76<=_z2al7i),_zgsfrl,0) | S76: =R76-Q76 | T76: =MAX(0,P76-S76) | U76: =IF(AND(B76,A76<=_zupe8l),_zb0m7l,0) | V76: =IF(AND(B76,A76<=_zupe8l),_zm1wss,0) | W76: =IF(AND(B76,A76<=_zhf3a4),_zdqt32,0) | X76: =IF((_zhsdpd="是"),IF(A76<=3,0,IF(A76<=6,0.5,1)),1) | Y76: =_zrzkf6*X76+(1-_zrzkf6) | Z76: =IF(B76,G76-_zkfhzg-O76-U76-W76-K76,0) | AA76: =MAX(0,-Z75) | AB76: =MIN(AA75,MAX(0,(AE75+AD75+AC75+AB75+AA75)-AF75)) | AC76: =MIN(AB75,MAX(0,(AE75+AD75+AC75+AB75)-AF75)) | AD76: =MIN(AC75,MAX(0,(AE75+AD75+AC75)-AF75)) | AE76: =MIN(AD75,MAX(0,(AE75+AD75)-AF75)) | AF76: =MIN(MAX(Z76,0),AA76+AB76+AC76+AD76+AE76) | AG76: =MAX(Z76,0)-AF76 | AH76: =AG76*_zs8hxw*Y76 | AI76: =IF(B76,G76-_zkfhzg-O76-V76-W76-K76-Q76,0) | AJ76: =MAX(0,-AI75) | AK76: =MIN(AJ75,MAX(0,(AN75+AM75+AL75+AK75+AJ75)-AO75)) | AL76: =MIN(AK75,MAX(0,(AN75+AM75+AL75+AK75)-AO75)) | AM76: =MIN(AL75,MAX(0,(AN75+AM75+AL75)-AO75)) | AN76: =MIN(AM75,MAX(0,(AN75+AM75)-AO75)) | AO76: =MIN(MAX(AI76,0),AJ76+AK76+AL76+AM76+AN76) | AP76: =MAX(AI76,0)-AO76 | AQ76: =AP76*_zs8hxw*Y76 | AR76: =IF(A76=_zx5hja,_zlajvq,0) | AS76: =IF(A76=_zx5hja,_zyh8pc,0) | AT76: =IF(B76,F76-_zkfhzg-M76-O76-I76+AR76,0) | AU76: =AT76-AH76 | AV76: =IF(B76,F76-_zkfhzg-M76-O76-I76-R76-AQ76+AS76-IF(AND(A76=_zx5hja,_z2al7i>_zx5hja),T76,0),0) | AW76: =AW75+AU76 | AX76: =IF(AND(AW75<0,AW76>=0,AU76>0),1,0) | AY76: =AU76/(1+_zawtbl)^A76 | AZ76: =AZ75+AY76 | BA76: =IF(AND(AZ75<0,AZ76>=0,AY76>0),1,0) | BB76: =_zs8nv3*C76 | BC76: =IF(B76,_zkfhzg+K76-AR76,0) | BD76: =IF(AT76=0,BD75,SIGN(AT76)) | BE76: =BE75+IF(OR(AT76=0,BD75=0),0,IF(SIGN(AT76)<>BD75,1,0)) | BF76: =IF(AU76=0,BF75,SIGN(AU76)) | BG76: =BG75+IF(OR(AU76=0,BF75=0),0,IF(SIGN(AU76)<>BF75,1,0)) | BH76: =IF(AV76=0,BH75,SIGN(AV76)) | BI76: =BI75+IF(OR(AV76=0,BH75=0),0,IF(SIGN(AV76)<>BH75,1,0))
A77: 11 | B77: =AND(A77>=1,A77<=_zx5hja) | C77: =IF(B77,(1-_zg5443)^(A77-1),0) | D77: =_zt11ik*C77 | E77: =_z5gr99*C77 | F77: =_zk8d4f*D77+_zsw7bq*E77 | G77: =F77/(1+0.13) | H77: =F77-G77 | I77: =IF(AND(B77,A77=_ztfkfy),_z67r2o*_z0m7ys,0) | J77: =I77*0.13/(1+0.13) | K77: =I77-J77 | L77: =N76+J77 | M77: =MAX(0,H77-L77) | N77: =MAX(0,L77-H77) | O77: =M77*0.12 | P77: =T76 | Q77: =IF(AND(B77,A77<=_z2al7i),P77*_zyywx7,0) | R77: =IF(AND(B77,A77<=_z2al7i),_zgsfrl,0) | S77: =R77-Q77 | T77: =MAX(0,P77-S77) | U77: =IF(AND(B77,A77<=_zupe8l),_zb0m7l,0) | V77: =IF(AND(B77,A77<=_zupe8l),_zm1wss,0) | W77: =IF(AND(B77,A77<=_zhf3a4),_zdqt32,0) | X77: =IF((_zhsdpd="是"),IF(A77<=3,0,IF(A77<=6,0.5,1)),1) | Y77: =_zrzkf6*X77+(1-_zrzkf6) | Z77: =IF(B77,G77-_zkfhzg-O77-U77-W77-K77,0) | AA77: =MAX(0,-Z76) | AB77: =MIN(AA76,MAX(0,(AE76+AD76+AC76+AB76+AA76)-AF76)) | AC77: =MIN(AB76,MAX(0,(AE76+AD76+AC76+AB76)-AF76)) | AD77: =MIN(AC76,MAX(0,(AE76+AD76+AC76)-AF76)) | AE77: =MIN(AD76,MAX(0,(AE76+AD76)-AF76)) | AF77: =MIN(MAX(Z77,0),AA77+AB77+AC77+AD77+AE77) | AG77: =MAX(Z77,0)-AF77 | AH77: =AG77*_zs8hxw*Y77 | AI77: =IF(B77,G77-_zkfhzg-O77-V77-W77-K77-Q77,0) | AJ77: =MAX(0,-AI76) | AK77: =MIN(AJ76,MAX(0,(AN76+AM76+AL76+AK76+AJ76)-AO76)) | AL77: =MIN(AK76,MAX(0,(AN76+AM76+AL76+AK76)-AO76)) | AM77: =MIN(AL76,MAX(0,(AN76+AM76+AL76)-AO76)) | AN77: =MIN(AM76,MAX(0,(AN76+AM76)-AO76)) | AO77: =MIN(MAX(AI77,0),AJ77+AK77+AL77+AM77+AN77) | AP77: =MAX(AI77,0)-AO77 | AQ77: =AP77*_zs8hxw*Y77 | AR77: =IF(A77=_zx5hja,_zlajvq,0) | AS77: =IF(A77=_zx5hja,_zyh8pc,0) | AT77: =IF(B77,F77-_zkfhzg-M77-O77-I77+AR77,0) | AU77: =AT77-AH77 | AV77: =IF(B77,F77-_zkfhzg-M77-O77-I77-R77-AQ77+AS77-IF(AND(A77=_zx5hja,_z2al7i>_zx5hja),T77,0),0) | AW77: =AW76+AU77 | AX77: =IF(AND(AW76<0,AW77>=0,AU77>0),1,0) | AY77: =AU77/(1+_zawtbl)^A77 | AZ77: =AZ76+AY77 | BA77: =IF(AND(AZ76<0,AZ77>=0,AY77>0),1,0) | BB77: =_zs8nv3*C77 | BC77: =IF(B77,_zkfhzg+K77-AR77,0) | BD77: =IF(AT77=0,BD76,SIGN(AT77)) | BE77: =BE76+IF(OR(AT77=0,BD76=0),0,IF(SIGN(AT77)<>BD76,1,0)) | BF77: =IF(AU77=0,BF76,SIGN(AU77)) | BG77: =BG76+IF(OR(AU77=0,BF76=0),0,IF(SIGN(AU77)<>BF76,1,0)) | BH77: =IF(AV77=0,BH76,SIGN(AV77)) | BI77: =BI76+IF(OR(AV77=0,BH76=0),0,IF(SIGN(AV77)<>BH76,1,0))
A78: 12 | B78: =AND(A78>=1,A78<=_zx5hja) | C78: =IF(B78,(1-_zg5443)^(A78-1),0) | D78: =_zt11ik*C78 | E78: =_z5gr99*C78 | F78: =_zk8d4f*D78+_zsw7bq*E78 | G78: =F78/(1+0.13) | H78: =F78-G78 | I78: =IF(AND(B78,A78=_ztfkfy),_z67r2o*_z0m7ys,0) | J78: =I78*0.13/(1+0.13) | K78: =I78-J78 | L78: =N77+J78 | M78: =MAX(0,H78-L78) | N78: =MAX(0,L78-H78) | O78: =M78*0.12 | P78: =T77 | Q78: =IF(AND(B78,A78<=_z2al7i),P78*_zyywx7,0) | R78: =IF(AND(B78,A78<=_z2al7i),_zgsfrl,0) | S78: =R78-Q78 | T78: =MAX(0,P78-S78) | U78: =IF(AND(B78,A78<=_zupe8l),_zb0m7l,0) | V78: =IF(AND(B78,A78<=_zupe8l),_zm1wss,0) | W78: =IF(AND(B78,A78<=_zhf3a4),_zdqt32,0) | X78: =IF((_zhsdpd="是"),IF(A78<=3,0,IF(A78<=6,0.5,1)),1) | Y78: =_zrzkf6*X78+(1-_zrzkf6) | Z78: =IF(B78,G78-_zkfhzg-O78-U78-W78-K78,0) | AA78: =MAX(0,-Z77) | AB78: =MIN(AA77,MAX(0,(AE77+AD77+AC77+AB77+AA77)-AF77)) | AC78: =MIN(AB77,MAX(0,(AE77+AD77+AC77+AB77)-AF77)) | AD78: =MIN(AC77,MAX(0,(AE77+AD77+AC77)-AF77)) | AE78: =MIN(AD77,MAX(0,(AE77+AD77)-AF77)) | AF78: =MIN(MAX(Z78,0),AA78+AB78+AC78+AD78+AE78) | AG78: =MAX(Z78,0)-AF78 | AH78: =AG78*_zs8hxw*Y78 | AI78: =IF(B78,G78-_zkfhzg-O78-V78-W78-K78-Q78,0) | AJ78: =MAX(0,-AI77) | AK78: =MIN(AJ77,MAX(0,(AN77+AM77+AL77+AK77+AJ77)-AO77)) | AL78: =MIN(AK77,MAX(0,(AN77+AM77+AL77+AK77)-AO77)) | AM78: =MIN(AL77,MAX(0,(AN77+AM77+AL77)-AO77)) | AN78: =MIN(AM77,MAX(0,(AN77+AM77)-AO77)) | AO78: =MIN(MAX(AI78,0),AJ78+AK78+AL78+AM78+AN78) | AP78: =MAX(AI78,0)-AO78 | AQ78: =AP78*_zs8hxw*Y78 | AR78: =IF(A78=_zx5hja,_zlajvq,0) | AS78: =IF(A78=_zx5hja,_zyh8pc,0) | AT78: =IF(B78,F78-_zkfhzg-M78-O78-I78+AR78,0) | AU78: =AT78-AH78 | AV78: =IF(B78,F78-_zkfhzg-M78-O78-I78-R78-AQ78+AS78-IF(AND(A78=_zx5hja,_z2al7i>_zx5hja),T78,0),0) | AW78: =AW77+AU78 | AX78: =IF(AND(AW77<0,AW78>=0,AU78>0),1,0) | AY78: =AU78/(1+_zawtbl)^A78 | AZ78: =AZ77+AY78 | BA78: =IF(AND(AZ77<0,AZ78>=0,AY78>0),1,0) | BB78: =_zs8nv3*C78 | BC78: =IF(B78,_zkfhzg+K78-AR78,0) | BD78: =IF(AT78=0,BD77,SIGN(AT78)) | BE78: =BE77+IF(OR(AT78=0,BD77=0),0,IF(SIGN(AT78)<>BD77,1,0)) | BF78: =IF(AU78=0,BF77,SIGN(AU78)) | BG78: =BG77+IF(OR(AU78=0,BF77=0),0,IF(SIGN(AU78)<>BF77,1,0)) | BH78: =IF(AV78=0,BH77,SIGN(AV78)) | BI78: =BI77+IF(OR(AV78=0,BH77=0),0,IF(SIGN(AV78)<>BH77,1,0))
... A91: 25 | B91: =AND(A91>=1,A91<=_zx5hja) | C91: =IF(B91,(1-_zg5443)^(A91-1),0) | D91: =_zt11ik*C91 | E91: =_z5gr99*C91 | F91: =_zk8d4f*D91+_zsw7bq*E91 | G91: =F91/(1+0.13) | H91: =F91-G91 | I91: =IF(AND(B91,A91=_ztfkfy),_z67r2o*_z0m7ys,0) | J91: =I91*0.13/(1+0.13) | K91: =I91-J91 | L91: =N90+J91 | M91: =MAX(0,H91-L91) | N91: =MAX(0,L91-H91) | O91: =M91*0.12 | P91: =T90 | Q91: =IF(AND(B91,A91<=_z2al7i),P91*_zyywx7,0) | R91: =IF(AND(B91,A91<=_z2al7i),_zgsfrl,0) | S91: =R91-Q91 | T91: =MAX(0,P91-S91) | U91: =IF(AND(B91,A91<=_zupe8l),_zb0m7l,0) | V91: =IF(AND(B91,A91<=_zupe8l),_zm1wss,0) | W91: =IF(AND(B91,A91<=_zhf3a4),_zdqt32,0) | X91: =IF((_zhsdpd="是"),IF(A91<=3,0,IF(A91<=6,0.5,1)),1) | Y91: =_zrzkf6*X91+(1-_zrzkf6) | Z91: =IF(B91,G91-_zkfhzg-O91-U91-W91-K91,0) | AA91: =MAX(0,-Z90) | AB91: =MIN(AA90,MAX(0,(AE90+AD90+AC90+AB90+AA90)-AF90)) | AC91: =MIN(AB90,MAX(0,(AE90+AD90+AC90+AB90)-AF90)) | AD91: =MIN(AC90,MAX(0,(AE90+AD90+AC90)-AF90)) | AE91: =MIN(AD90,MAX(0,(AE90+AD90)-AF90)) | AF91: =MIN(MAX(Z91,0),AA91+AB91+AC91+AD91+AE91) | AG91: =MAX(Z91,0)-AF91 | AH91: =AG91*_zs8hxw*Y91 | AI91: =IF(B91,G91-_zkfhzg-O91-V91-W91-K91-Q91,0) | AJ91: =MAX(0,-AI90) | AK91: =MIN(AJ90,MAX(0,(AN90+AM90+AL90+AK90+AJ90)-AO90)) | AL91: =MIN(AK90,MAX(0,(AN90+AM90+AL90+AK90)-AO90)) | AM91: =MIN(AL90,MAX(0,(AN90+AM90+AL90)-AO90)) | AN91: =MIN(AM90,MAX(0,(AN90+AM90)-AO90)) | AO91: =MIN(MAX(AI91,0),AJ91+AK91+AL91+AM91+AN91) | AP91: =MAX(AI91,0)-AO91 | AQ91: =AP91*_zs8hxw*Y91 | AR91: =IF(A91=_zx5hja,_zlajvq,0) | AS91: =IF(A91=_zx5hja,_zyh8pc,0) | AT91: =IF(B91,F91-_zkfhzg-M91-O91-I91+AR91,0) | AU91: =AT91-AH91 | AV91: =IF(B91,F91-_zkfhzg-M91-O91-I91-R91-AQ91+AS91-IF(AND(A91=_zx5hja,_z2al7i>_zx5hja),T91,0),0) | AW91: =AW90+AU91 | AX91: =IF(AND(AW90<0,AW91>=0,AU91>0),1,0) | AY91: =AU91/(1+_zawtbl)^A91 | AZ91: =AZ90+AY91 | BA91: =IF(AND(AZ90<0,AZ91>=0,AY91>0),1,0) | BB91: =_zs8nv3*C91 | BC91: =IF(B91,_zkfhzg+K91-AR91,0) | BD91: =IF(AT91=0,BD90,SIGN(AT91)) | BE91: =BE90+IF(OR(AT91=0,BD90=0),0,IF(SIGN(AT91)<>BD90,1,0)) | BF91: =IF(AU91=0,BF90,SIGN(AU91)) | BG91: =BG90+IF(OR(AU91=0,BF90=0),0,IF(SIGN(AU91)<>BF90,1,0)) | BH91: =IF(AV91=0,BH90,SIGN(AV91)) | BI91: =BI90+IF(OR(AV91=0,BH90=0),0,IF(SIGN(AV91)<>BH90,1,0))
A93: chk_pre_lo | B93: =SUMPRODUCT(_zu5jm5,0.01^-_zmuh0g)
A94: chk_pre_hi | B94: =SUMPRODUCT(_zu5jm5,4^-_zmuh0g)
A95: chk_post_lo | B95: =SUMPRODUCT(_zzpzma,0.01^-_zmuh0g)
A96: chk_post_hi | B96: =SUMPRODUCT(_zzpzma,4^-_zmuh0g)
A97: chk_eq_lo | B97: =SUMPRODUCT(_z47e1n,0.01^-_zmuh0g)
A98: chk_eq_hi | B98: =SUMPRODUCT(_z47e1n,4^-_zmuh0g)
A99: irr_pre | B99: =IF(_z7fj0w>25,"运营期超25年·请用网页版测算",IF(_zsqbm8*_zzj3wj>0,IF(BE91>1,"非常规现金流，须人工复核","全周期未回收"),IFERROR(IRR(_zu5jm5),"—")))
A100: irr_post | B100: =IF(_z7fj0w>25,"运营期超25年·请用网页版测算",IF(_zqsho0*_zpy13v>0,IF(BG91>1,"非常规现金流，须人工复核","全周期未回收"),IFERROR(IRR(_zzpzma),"—")))
A101: irr_eq | B101: =IF(_z7fj0w>25,"运营期超25年·请用网页版测算",IF(_zxdbxd*_ztsxiq>0,IF(BI91>1,"非常规现金流，须人工复核","全周期未回收"),IFERROR(IRR(_z47e1n),"—")))
A102: npv | B102: =IF(_z7fj0w>25,"运营期超25年·请用网页版测算",INDEX(_zzpzma,1)+NPV(_zawtbl,_zylg1g))
A103: payback_s | B103: =IF(_z7fj0w>25,"运营期超25年·请用网页版测算",IFERROR(MATCH(1,_zqxysi,0)-2+ABS(INDEX(_zhb49w,MATCH(1,_zqxysi,0)-1))/INDEX(_zzpzma,MATCH(1,_zqxysi,0)),"超运营期"))
A104: payback_d | B104: =IF(_z7fj0w>25,"运营期超25年·请用网页版测算",IFERROR(MATCH(1,_zcoe8g,0)-2+ABS(INDEX(_zn8bpc,MATCH(1,_zcoe8g,0)-1))/INDEX(_zd9fqm,MATCH(1,_zcoe8g,0)),"超运营期"))
A105: lcoe | B105: =IF(_z7fj0w>25,"运营期超25年·请用网页版测算",IF(NPV(_zawtbl,_zs6qdd)>0,(_z2nx0n+_zfraqw+NPV(_zawtbl,_zzvb05))/NPV(_zawtbl,_zs6qdd),"—"))
